[{"type":"SceneTagged","value":{"sceneId":"unknown","tag":{"name":"Linux 6.5.0-1018-azure","type":"platform","platformName":"Linux","platformVersion":"6.5.0-1018-azure"},"timestamp":"2024-05-12T06:19:59.935Z"}},{"type":"SceneTagged","value":{"sceneId":"unknown","tag":{"name":"chromium 121.0.6167.57","type":"browser","browserName":"chromium","browserVersion":"121.0.6167.57"},"timestamp":"2024-05-12T06:19:59.936Z"}},{"type":"TaskStarts","value":{"activityId":"v4uz37wvecc31wmu3vlee1jq","details":{"name":"Alice starts with a list containing 1 items","location":{"column":41,"line":39,"path":"/home/runner/work/serenity-js-realworld-app-demo/serenity-js-realworld-app-demo/spec/multi-actor_scenarios.spec.ts"}},"sceneId":"unknown","timestamp":"2024-05-12T06:19:59.944Z"}},{"type":"TaskStarts","value":{"activityId":"ypyiwtsdqba7vi3dtexm761f","details":{"name":"Alice starts with an empty todo list","location":{"column":9,"line":18,"path":"/home/runner/work/serenity-js-realworld-app-demo/serenity-js-realworld-app-demo/spec/todo-list-app/TodoApp/tasks.ts"}},"sceneId":"unknown","timestamp":"2024-05-12T06:19:59.945Z"}},{"type":"InteractionStarts","value":{"activityId":"s9leig0lmumktubsi58ycqf0","details":{"name":"Alice navigates to '/'","location":{"column":18,"line":9,"path":"/home/runner/work/serenity-js-realworld-app-demo/serenity-js-realworld-app-demo/spec/todo-list-app/TodoApp/tasks.ts"}},"sceneId":"unknown","timestamp":"2024-05-12T06:19:59.945Z"}},{"type":"InteractionFinished","value":{"activityId":"s9leig0lmumktubsi58ycqf0","details":{"name":"Alice navigates to '/'","location":{"column":18,"line":9,"path":"/home/runner/work/serenity-js-realworld-app-demo/serenity-js-realworld-app-demo/spec/todo-list-app/TodoApp/tasks.ts"}},"outcome":{"code":64},"sceneId":"unknown","timestamp":"2024-05-12T06:20:00.175Z"}},{"type":"InteractionStarts","value":{"activityId":"k6u18r3fkg077851e6wdmd3m","details":{"name":"Alice ensures that website title does equal 'Serenity/JS TodoApp'","location":{"column":41,"line":39,"path":"/home/runner/work/serenity-js-realworld-app-demo/serenity-js-realworld-app-demo/spec/multi-actor_scenarios.spec.ts"}},"sceneId":"unknown","timestamp":"2024-05-12T06:20:00.187Z"}},{"type":"InteractionFinished","value":{"activityId":"k6u18r3fkg077851e6wdmd3m","details":{"name":"Alice ensures that website title does equal 'Serenity/JS TodoApp'","location":{"column":41,"line":39,"path":"/home/runner/work/serenity-js-realworld-app-demo/serenity-js-realworld-app-demo/spec/multi-actor_scenarios.spec.ts"}},"outcome":{"code":64},"sceneId":"unknown","timestamp":"2024-05-12T06:20:00.192Z"}},{"type":"TaskFinished","value":{"activityId":"ypyiwtsdqba7vi3dtexm761f","details":{"name":"Alice starts with an empty todo list","location":{"column":9,"line":18,"path":"/home/runner/work/serenity-js-realworld-app-demo/serenity-js-realworld-app-demo/spec/todo-list-app/TodoApp/tasks.ts"}},"outcome":{"code":64},"sceneId":"unknown","timestamp":"2024-05-12T06:20:00.202Z"}},{"type":"TaskStarts","value":{"activityId":"aapyohche3sxw7xncmewvgtl","details":{"name":"Alice records an item called 'Feed the cat'","location":{"column":18,"line":19,"path":"/home/runner/work/serenity-js-realworld-app-demo/serenity-js-realworld-app-demo/spec/todo-list-app/TodoApp/tasks.ts"}},"sceneId":"unknown","timestamp":"2024-05-12T06:20:00.213Z"}},{"type":"InteractionStarts","value":{"activityId":"glq0yhodqfqz0e1heo850pze","details":{"name":"Alice enters 'Feed the cat' into \"What needs to be done?\" input box","location":{"column":30,"line":12,"path":"/home/runner/work/serenity-js-realworld-app-demo/serenity-js-realworld-app-demo/spec/todo-list-app/TodoItem/tasks.ts"}},"sceneId":"unknown","timestamp":"2024-05-12T06:20:00.213Z"}},{"type":"InteractionFinished","value":{"activityId":"glq0yhodqfqz0e1heo850pze","details":{"name":"Alice enters 'Feed the cat' into \"What needs to be done?\" input box","location":{"column":30,"line":12,"path":"/home/runner/work/serenity-js-realworld-app-demo/serenity-js-realworld-app-demo/spec/todo-list-app/TodoItem/tasks.ts"}},"outcome":{"code":64},"sceneId":"unknown","timestamp":"2024-05-12T06:20:00.242Z"}},{"type":"InteractionStarts","value":{"activityId":"gck1cis6dgasb0q6o0rzf608","details":{"name":"Alice presses key Enter in \"What needs to be done?\" input box","location":{"column":32,"line":13,"path":"/home/runner/work/serenity-js-realworld-app-demo/serenity-js-realworld-app-demo/spec/todo-list-app/TodoItem/tasks.ts"}},"sceneId":"unknown","timestamp":"2024-05-12T06:20:00.253Z"}},{"type":"InteractionFinished","value":{"activityId":"gck1cis6dgasb0q6o0rzf608","details":{"name":"Alice presses key Enter in \"What needs to be done?\" input box","location":{"column":32,"line":13,"path":"/home/runner/work/serenity-js-realworld-app-demo/serenity-js-realworld-app-demo/spec/todo-list-app/TodoItem/tasks.ts"}},"outcome":{"code":64},"sceneId":"unknown","timestamp":"2024-05-12T06:20:00.281Z"}},{"type":"InteractionStarts","value":{"activityId":"njtzswl8vaj6dj7q0t4mljfd","details":{"name":"Alice waits until displayed items does contain 'Feed the cat'","location":{"column":14,"line":14,"path":"/home/runner/work/serenity-js-realworld-app-demo/serenity-js-realworld-app-demo/spec/todo-list-app/TodoItem/tasks.ts"}},"sceneId":"unknown","timestamp":"2024-05-12T06:20:00.292Z"}},{"type":"InteractionFinished","value":{"activityId":"njtzswl8vaj6dj7q0t4mljfd","details":{"name":"Alice waits until displayed items does contain 'Feed the cat'","location":{"column":14,"line":14,"path":"/home/runner/work/serenity-js-realworld-app-demo/serenity-js-realworld-app-demo/spec/todo-list-app/TodoItem/tasks.ts"}},"outcome":{"code":64},"sceneId":"unknown","timestamp":"2024-05-12T06:20:00.310Z"}},{"type":"TaskFinished","value":{"activityId":"aapyohche3sxw7xncmewvgtl","details":{"name":"Alice records an item called 'Feed the cat'","location":{"column":18,"line":19,"path":"/home/runner/work/serenity-js-realworld-app-demo/serenity-js-realworld-app-demo/spec/todo-list-app/TodoApp/tasks.ts"}},"outcome":{"code":64},"sceneId":"unknown","timestamp":"2024-05-12T06:20:00.321Z"}},{"type":"TaskFinished","value":{"activityId":"v4uz37wvecc31wmu3vlee1jq","details":{"name":"Alice starts with a list containing 1 items","location":{"column":41,"line":39,"path":"/home/runner/work/serenity-js-realworld-app-demo/serenity-js-realworld-app-demo/spec/multi-actor_scenarios.spec.ts"}},"outcome":{"code":64},"sceneId":"unknown","timestamp":"2024-05-12T06:20:00.331Z"}},{"type":"TaskStarts","value":{"activityId":"izecrdtbjs0kfc84bn6o0urk","details":{"name":"Bob starts with a list containing 1 items","location":{"column":41,"line":45,"path":"/home/runner/work/serenity-js-realworld-app-demo/serenity-js-realworld-app-demo/spec/multi-actor_scenarios.spec.ts"}},"sceneId":"unknown","timestamp":"2024-05-12T06:20:00.353Z"}},{"type":"TaskStarts","value":{"activityId":"gslm4faif687svxedblc1y2u","details":{"name":"Bob starts with an empty todo list","location":{"column":9,"line":18,"path":"/home/runner/work/serenity-js-realworld-app-demo/serenity-js-realworld-app-demo/spec/todo-list-app/TodoApp/tasks.ts"}},"sceneId":"unknown","timestamp":"2024-05-12T06:20:00.353Z"}},{"type":"InteractionStarts","value":{"activityId":"xp61uold6oddy0ts1h92zeu5","details":{"name":"Bob navigates to '/'","location":{"column":18,"line":9,"path":"/home/runner/work/serenity-js-realworld-app-demo/serenity-js-realworld-app-demo/spec/todo-list-app/TodoApp/tasks.ts"}},"sceneId":"unknown","timestamp":"2024-05-12T06:20:00.354Z"}},{"type":"InteractionFinished","value":{"activityId":"xp61uold6oddy0ts1h92zeu5","details":{"name":"Bob navigates to '/'","location":{"column":18,"line":9,"path":"/home/runner/work/serenity-js-realworld-app-demo/serenity-js-realworld-app-demo/spec/todo-list-app/TodoApp/tasks.ts"}},"outcome":{"code":64},"sceneId":"unknown","timestamp":"2024-05-12T06:20:00.519Z"}},{"type":"InteractionStarts","value":{"activityId":"a4fcas12w5kvrwq1pp28wf0b","details":{"name":"Bob ensures that website title does equal 'Serenity/JS TodoApp'","location":{"column":41,"line":45,"path":"/home/runner/work/serenity-js-realworld-app-demo/serenity-js-realworld-app-demo/spec/multi-actor_scenarios.spec.ts"}},"sceneId":"unknown","timestamp":"2024-05-12T06:20:00.531Z"}},{"type":"InteractionFinished","value":{"activityId":"a4fcas12w5kvrwq1pp28wf0b","details":{"name":"Bob ensures that website title does equal 'Serenity/JS TodoApp'","location":{"column":41,"line":45,"path":"/home/runner/work/serenity-js-realworld-app-demo/serenity-js-realworld-app-demo/spec/multi-actor_scenarios.spec.ts"}},"outcome":{"code":64},"sceneId":"unknown","timestamp":"2024-05-12T06:20:00.538Z"}},{"type":"TaskFinished","value":{"activityId":"gslm4faif687svxedblc1y2u","details":{"name":"Bob starts with an empty todo list","location":{"column":9,"line":18,"path":"/home/runner/work/serenity-js-realworld-app-demo/serenity-js-realworld-app-demo/spec/todo-list-app/TodoApp/tasks.ts"}},"outcome":{"code":64},"sceneId":"unknown","timestamp":"2024-05-12T06:20:00.548Z"}},{"type":"TaskStarts","value":{"activityId":"er4w0msdf9llxc46ur8h394p","details":{"name":"Bob records an item called 'Walk the dog'","location":{"column":18,"line":19,"path":"/home/runner/work/serenity-js-realworld-app-demo/serenity-js-realworld-app-demo/spec/todo-list-app/TodoApp/tasks.ts"}},"sceneId":"unknown","timestamp":"2024-05-12T06:20:00.559Z"}},{"type":"InteractionStarts","value":{"activityId":"udnbqw8slf2yid86bzx2h1an","details":{"name":"Bob enters 'Walk the dog' into \"What needs to be done?\" input box","location":{"column":30,"line":12,"path":"/home/runner/work/serenity-js-realworld-app-demo/serenity-js-realworld-app-demo/spec/todo-list-app/TodoItem/tasks.ts"}},"sceneId":"unknown","timestamp":"2024-05-12T06:20:00.560Z"}},{"type":"InteractionFinished","value":{"activityId":"udnbqw8slf2yid86bzx2h1an","details":{"name":"Bob enters 'Walk the dog' into \"What needs to be done?\" input box","location":{"column":30,"line":12,"path":"/home/runner/work/serenity-js-realworld-app-demo/serenity-js-realworld-app-demo/spec/todo-list-app/TodoItem/tasks.ts"}},"outcome":{"code":64},"sceneId":"unknown","timestamp":"2024-05-12T06:20:00.597Z"}},{"type":"InteractionStarts","value":{"activityId":"e622vddb1d4mlazx2d9sprgx","details":{"name":"Bob presses key Enter in \"What needs to be done?\" input box","location":{"column":32,"line":13,"path":"/home/runner/work/serenity-js-realworld-app-demo/serenity-js-realworld-app-demo/spec/todo-list-app/TodoItem/tasks.ts"}},"sceneId":"unknown","timestamp":"2024-05-12T06:20:00.609Z"}},{"type":"InteractionFinished","value":{"activityId":"e622vddb1d4mlazx2d9sprgx","details":{"name":"Bob presses key Enter in \"What needs to be done?\" input box","location":{"column":32,"line":13,"path":"/home/runner/work/serenity-js-realworld-app-demo/serenity-js-realworld-app-demo/spec/todo-list-app/TodoItem/tasks.ts"}},"outcome":{"code":64},"sceneId":"unknown","timestamp":"2024-05-12T06:20:00.635Z"}},{"type":"InteractionStarts","value":{"activityId":"wp20kezy87xxm94k44xzn8uz","details":{"name":"Bob waits until displayed items does contain 'Walk the dog'","location":{"column":14,"line":14,"path":"/home/runner/work/serenity-js-realworld-app-demo/serenity-js-realworld-app-demo/spec/todo-list-app/TodoItem/tasks.ts"}},"sceneId":"unknown","timestamp":"2024-05-12T06:20:00.647Z"}},{"type":"InteractionFinished","value":{"activityId":"wp20kezy87xxm94k44xzn8uz","details":{"name":"Bob waits until displayed items does contain 'Walk the dog'","location":{"column":14,"line":14,"path":"/home/runner/work/serenity-js-realworld-app-demo/serenity-js-realworld-app-demo/spec/todo-list-app/TodoItem/tasks.ts"}},"outcome":{"code":64},"sceneId":"unknown","timestamp":"2024-05-12T06:20:00.665Z"}},{"type":"TaskFinished","value":{"activityId":"er4w0msdf9llxc46ur8h394p","details":{"name":"Bob records an item called 'Walk the dog'","location":{"column":18,"line":19,"path":"/home/runner/work/serenity-js-realworld-app-demo/serenity-js-realworld-app-demo/spec/todo-list-app/TodoApp/tasks.ts"}},"outcome":{"code":64},"sceneId":"unknown","timestamp":"2024-05-12T06:20:00.675Z"}},{"type":"TaskFinished","value":{"activityId":"izecrdtbjs0kfc84bn6o0urk","details":{"name":"Bob starts with a list containing 1 items","location":{"column":41,"line":45,"path":"/home/runner/work/serenity-js-realworld-app-demo/serenity-js-realworld-app-demo/spec/multi-actor_scenarios.spec.ts"}},"outcome":{"code":64},"sceneId":"unknown","timestamp":"2024-05-12T06:20:00.685Z"}},{"type":"InteractionStarts","value":{"activityId":"u0eewsjno40fzib3szvq09j0","details":{"name":"Alice ensures that displayed items does equal [ 'Feed the cat' ]","location":{"column":24,"line":51,"path":"/home/runner/work/serenity-js-realworld-app-demo/serenity-js-realworld-app-demo/spec/multi-actor_scenarios.spec.ts"}},"sceneId":"unknown","timestamp":"2024-05-12T06:20:00.698Z"}},{"type":"InteractionFinished","value":{"activityId":"u0eewsjno40fzib3szvq09j0","details":{"name":"Alice ensures that displayed items does equal [ 'Feed the cat' ]","location":{"column":24,"line":51,"path":"/home/runner/work/serenity-js-realworld-app-demo/serenity-js-realworld-app-demo/spec/multi-actor_scenarios.spec.ts"}},"outcome":{"code":64},"sceneId":"unknown","timestamp":"2024-05-12T06:20:00.705Z"}},{"type":"InteractionStarts","value":{"activityId":"y9oex862kme220f52xi1l2rr","details":{"name":"Bob ensures that displayed items does equal [ 'Walk the dog' ]","location":{"column":24,"line":57,"path":"/home/runner/work/serenity-js-realworld-app-demo/serenity-js-realworld-app-demo/spec/multi-actor_scenarios.spec.ts"}},"sceneId":"unknown","timestamp":"2024-05-12T06:20:00.719Z"}},{"type":"InteractionFinished","value":{"activityId":"y9oex862kme220f52xi1l2rr","details":{"name":"Bob ensures that displayed items does equal [ 'Walk the dog' ]","location":{"column":24,"line":57,"path":"/home/runner/work/serenity-js-realworld-app-demo/serenity-js-realworld-app-demo/spec/multi-actor_scenarios.spec.ts"}},"outcome":{"code":64},"sceneId":"unknown","timestamp":"2024-05-12T06:20:00.726Z"}},{"type":"SceneFinishes","value":{"sceneId":"unknown","timestamp":"2024-05-12T06:20:00.737Z"}},{"type":"AsyncOperationAttempted","value":{"correlationId":"qc687gripkrx4zcgpvnuu88u","description":"Dismissing Alice...","name":"Stage","timestamp":"2024-05-12T06:20:00.748Z"}},{"type":"AsyncOperationAttempted","value":{"correlationId":"nbbinxxu57ec96xg919hr4p4","description":"Dismissing Bob...","name":"Stage","timestamp":"2024-05-12T06:20:00.748Z"}},{"type":"AsyncOperationCompleted","value":{"correlationId":"qc687gripkrx4zcgpvnuu88u","timestamp":"2024-05-12T06:20:00.754Z"}},{"type":"AsyncOperationCompleted","value":{"correlationId":"nbbinxxu57ec96xg919hr4p4","timestamp":"2024-05-12T06:20:00.761Z"}}]