[{"type":"SceneTagged","value":{"sceneId":"unknown","tag":{"name":"Linux 6.5.0-1018-azure","type":"platform","platformName":"Linux","platformVersion":"6.5.0-1018-azure"},"timestamp":"2024-04-29T21:31:50.845Z"}},{"type":"SceneTagged","value":{"sceneId":"unknown","tag":{"name":"webkit 17.4","type":"browser","browserName":"webkit","browserVersion":"17.4"},"timestamp":"2024-04-29T21:31:50.977Z"}},{"type":"TaskStarts","value":{"activityId":"kp5kcs2prqc0j7xpecz6rz99","details":{"name":"Alice starts with an empty todo list","location":{"column":37,"line":38,"path":"/home/runner/work/serenity-js-realworld-app-demo/serenity-js-realworld-app-demo/spec/recording_items.spec.ts"}},"sceneId":"unknown","timestamp":"2024-04-29T21:31:50.996Z"}},{"type":"InteractionStarts","value":{"activityId":"q1s6rqkcsy2saeyzu27ne5t2","details":{"name":"Alice navigates to '/'","location":{"column":18,"line":9,"path":"/home/runner/work/serenity-js-realworld-app-demo/serenity-js-realworld-app-demo/spec/todo-list-app/TodoApp/tasks.ts"}},"sceneId":"unknown","timestamp":"2024-04-29T21:31:50.996Z"}},{"type":"InteractionFinished","value":{"activityId":"q1s6rqkcsy2saeyzu27ne5t2","details":{"name":"Alice navigates to '/'","location":{"column":18,"line":9,"path":"/home/runner/work/serenity-js-realworld-app-demo/serenity-js-realworld-app-demo/spec/todo-list-app/TodoApp/tasks.ts"}},"outcome":{"code":64},"sceneId":"unknown","timestamp":"2024-04-29T21:31:51.298Z"}},{"type":"InteractionStarts","value":{"activityId":"j6j6ewsyvqwjz03mxs66dasv","details":{"name":"Alice ensures that website title does equal 'Serenity/JS TodoApp'","location":{"column":37,"line":38,"path":"/home/runner/work/serenity-js-realworld-app-demo/serenity-js-realworld-app-demo/spec/recording_items.spec.ts"}},"sceneId":"unknown","timestamp":"2024-04-29T21:31:51.309Z"}},{"type":"InteractionFinished","value":{"activityId":"j6j6ewsyvqwjz03mxs66dasv","details":{"name":"Alice ensures that website title does equal 'Serenity/JS TodoApp'","location":{"column":37,"line":38,"path":"/home/runner/work/serenity-js-realworld-app-demo/serenity-js-realworld-app-demo/spec/recording_items.spec.ts"}},"outcome":{"code":64},"sceneId":"unknown","timestamp":"2024-04-29T21:31:51.316Z"}},{"type":"TaskFinished","value":{"activityId":"kp5kcs2prqc0j7xpecz6rz99","details":{"name":"Alice starts with an empty todo list","location":{"column":37,"line":38,"path":"/home/runner/work/serenity-js-realworld-app-demo/serenity-js-realworld-app-demo/spec/recording_items.spec.ts"}},"outcome":{"code":64},"sceneId":"unknown","timestamp":"2024-04-29T21:31:51.327Z"}},{"type":"TaskStarts","value":{"activityId":"c5e32cv48ey4wb7qupymhb0y","details":{"name":"Alice records an item called 'buy some cheese'","location":{"column":27,"line":40,"path":"/home/runner/work/serenity-js-realworld-app-demo/serenity-js-realworld-app-demo/spec/recording_items.spec.ts"}},"sceneId":"unknown","timestamp":"2024-04-29T21:31:51.338Z"}},{"type":"InteractionStarts","value":{"activityId":"mqo93tu7c4cv1g1aiy4d1qrt","details":{"name":"Alice enters 'buy some cheese' into \"What needs to be done?\" input box","location":{"column":30,"line":12,"path":"/home/runner/work/serenity-js-realworld-app-demo/serenity-js-realworld-app-demo/spec/todo-list-app/TodoItem/tasks.ts"}},"sceneId":"unknown","timestamp":"2024-04-29T21:31:51.339Z"}},{"type":"InteractionFinished","value":{"activityId":"mqo93tu7c4cv1g1aiy4d1qrt","details":{"name":"Alice enters 'buy some cheese' into \"What needs to be done?\" input box","location":{"column":30,"line":12,"path":"/home/runner/work/serenity-js-realworld-app-demo/serenity-js-realworld-app-demo/spec/todo-list-app/TodoItem/tasks.ts"}},"outcome":{"code":64},"sceneId":"unknown","timestamp":"2024-04-29T21:31:51.367Z"}},{"type":"InteractionStarts","value":{"activityId":"gon1cg2ld6vrigu07lfb6mc8","details":{"name":"Alice presses key Enter in \"What needs to be done?\" input box","location":{"column":32,"line":13,"path":"/home/runner/work/serenity-js-realworld-app-demo/serenity-js-realworld-app-demo/spec/todo-list-app/TodoItem/tasks.ts"}},"sceneId":"unknown","timestamp":"2024-04-29T21:31:51.379Z"}},{"type":"InteractionFinished","value":{"activityId":"gon1cg2ld6vrigu07lfb6mc8","details":{"name":"Alice presses key Enter in \"What needs to be done?\" input box","location":{"column":32,"line":13,"path":"/home/runner/work/serenity-js-realworld-app-demo/serenity-js-realworld-app-demo/spec/todo-list-app/TodoItem/tasks.ts"}},"outcome":{"code":64},"sceneId":"unknown","timestamp":"2024-04-29T21:31:51.422Z"}},{"type":"InteractionStarts","value":{"activityId":"fvzhukjv29wsklcxcmz0ja9j","details":{"name":"Alice waits until displayed items does contain 'buy some cheese'","location":{"column":14,"line":14,"path":"/home/runner/work/serenity-js-realworld-app-demo/serenity-js-realworld-app-demo/spec/todo-list-app/TodoItem/tasks.ts"}},"sceneId":"unknown","timestamp":"2024-04-29T21:31:51.433Z"}},{"type":"InteractionFinished","value":{"activityId":"fvzhukjv29wsklcxcmz0ja9j","details":{"name":"Alice waits until displayed items does contain 'buy some cheese'","location":{"column":14,"line":14,"path":"/home/runner/work/serenity-js-realworld-app-demo/serenity-js-realworld-app-demo/spec/todo-list-app/TodoItem/tasks.ts"}},"outcome":{"code":64},"sceneId":"unknown","timestamp":"2024-04-29T21:31:51.456Z"}},{"type":"TaskFinished","value":{"activityId":"c5e32cv48ey4wb7qupymhb0y","details":{"name":"Alice records an item called 'buy some cheese'","location":{"column":27,"line":40,"path":"/home/runner/work/serenity-js-realworld-app-demo/serenity-js-realworld-app-demo/spec/recording_items.spec.ts"}},"outcome":{"code":64},"sceneId":"unknown","timestamp":"2024-04-29T21:31:51.470Z"}},{"type":"InteractionStarts","value":{"activityId":"r08oery4kivkk39u82n0taki","details":{"name":"Alice ensures that displayed items does equal [ 'buy some cheese' ]","location":{"column":24,"line":42,"path":"/home/runner/work/serenity-js-realworld-app-demo/serenity-js-realworld-app-demo/spec/recording_items.spec.ts"}},"sceneId":"unknown","timestamp":"2024-04-29T21:31:51.481Z"}},{"type":"InteractionFinished","value":{"activityId":"r08oery4kivkk39u82n0taki","details":{"name":"Alice ensures that displayed items does equal [ 'buy some cheese' ]","location":{"column":24,"line":42,"path":"/home/runner/work/serenity-js-realworld-app-demo/serenity-js-realworld-app-demo/spec/recording_items.spec.ts"}},"outcome":{"code":64},"sceneId":"unknown","timestamp":"2024-04-29T21:31:51.488Z"}},{"type":"TaskStarts","value":{"activityId":"boc2a022jbjgyeldr8nimhj7","details":{"name":"Alice records an item called 'feed the cat'","location":{"column":27,"line":46,"path":"/home/runner/work/serenity-js-realworld-app-demo/serenity-js-realworld-app-demo/spec/recording_items.spec.ts"}},"sceneId":"unknown","timestamp":"2024-04-29T21:31:51.499Z"}},{"type":"InteractionStarts","value":{"activityId":"cgk6qu1jk4m5zq6rio0fh798","details":{"name":"Alice enters 'feed the cat' into \"What needs to be done?\" input box","location":{"column":30,"line":12,"path":"/home/runner/work/serenity-js-realworld-app-demo/serenity-js-realworld-app-demo/spec/todo-list-app/TodoItem/tasks.ts"}},"sceneId":"unknown","timestamp":"2024-04-29T21:31:51.499Z"}},{"type":"InteractionFinished","value":{"activityId":"cgk6qu1jk4m5zq6rio0fh798","details":{"name":"Alice enters 'feed the cat' into \"What needs to be done?\" input box","location":{"column":30,"line":12,"path":"/home/runner/work/serenity-js-realworld-app-demo/serenity-js-realworld-app-demo/spec/todo-list-app/TodoItem/tasks.ts"}},"outcome":{"code":64},"sceneId":"unknown","timestamp":"2024-04-29T21:31:51.508Z"}},{"type":"InteractionStarts","value":{"activityId":"myhr3baid0d6igqrpipu9rxe","details":{"name":"Alice presses key Enter in \"What needs to be done?\" input box","location":{"column":32,"line":13,"path":"/home/runner/work/serenity-js-realworld-app-demo/serenity-js-realworld-app-demo/spec/todo-list-app/TodoItem/tasks.ts"}},"sceneId":"unknown","timestamp":"2024-04-29T21:31:51.520Z"}},{"type":"InteractionFinished","value":{"activityId":"myhr3baid0d6igqrpipu9rxe","details":{"name":"Alice presses key Enter in \"What needs to be done?\" input box","location":{"column":32,"line":13,"path":"/home/runner/work/serenity-js-realworld-app-demo/serenity-js-realworld-app-demo/spec/todo-list-app/TodoItem/tasks.ts"}},"outcome":{"code":64},"sceneId":"unknown","timestamp":"2024-04-29T21:31:51.543Z"}},{"type":"InteractionStarts","value":{"activityId":"kedh0bestohifmjiq9y0ikz1","details":{"name":"Alice waits until displayed items does contain 'feed the cat'","location":{"column":14,"line":14,"path":"/home/runner/work/serenity-js-realworld-app-demo/serenity-js-realworld-app-demo/spec/todo-list-app/TodoItem/tasks.ts"}},"sceneId":"unknown","timestamp":"2024-04-29T21:31:51.554Z"}},{"type":"InteractionFinished","value":{"activityId":"kedh0bestohifmjiq9y0ikz1","details":{"name":"Alice waits until displayed items does contain 'feed the cat'","location":{"column":14,"line":14,"path":"/home/runner/work/serenity-js-realworld-app-demo/serenity-js-realworld-app-demo/spec/todo-list-app/TodoItem/tasks.ts"}},"outcome":{"code":64},"sceneId":"unknown","timestamp":"2024-04-29T21:31:51.576Z"}},{"type":"TaskFinished","value":{"activityId":"boc2a022jbjgyeldr8nimhj7","details":{"name":"Alice records an item called 'feed the cat'","location":{"column":27,"line":46,"path":"/home/runner/work/serenity-js-realworld-app-demo/serenity-js-realworld-app-demo/spec/recording_items.spec.ts"}},"outcome":{"code":64},"sceneId":"unknown","timestamp":"2024-04-29T21:31:51.586Z"}},{"type":"InteractionStarts","value":{"activityId":"el83at23781fric7cewcdook","details":{"name":"Alice ensures that displayed items does equal [ 'buy some cheese', 'feed the cat' ]","location":{"column":24,"line":48,"path":"/home/runner/work/serenity-js-realworld-app-demo/serenity-js-realworld-app-demo/spec/recording_items.spec.ts"}},"sceneId":"unknown","timestamp":"2024-04-29T21:31:51.598Z"}},{"type":"InteractionFinished","value":{"activityId":"el83at23781fric7cewcdook","details":{"name":"Alice ensures that displayed items does equal [ 'buy some cheese', 'feed the cat' ]","location":{"column":24,"line":48,"path":"/home/runner/work/serenity-js-realworld-app-demo/serenity-js-realworld-app-demo/spec/recording_items.spec.ts"}},"outcome":{"code":64},"sceneId":"unknown","timestamp":"2024-04-29T21:31:51.607Z"}},{"type":"InteractionStarts","value":{"activityId":"g5ckqifl8kzfk6x52debfhss","details":{"name":"Alice ensures that persisted items does equal displayed items","location":{"column":24,"line":55,"path":"/home/runner/work/serenity-js-realworld-app-demo/serenity-js-realworld-app-demo/spec/recording_items.spec.ts"}},"sceneId":"unknown","timestamp":"2024-04-29T21:31:51.618Z"}},{"type":"InteractionFinished","value":{"activityId":"g5ckqifl8kzfk6x52debfhss","details":{"name":"Alice ensures that persisted items does equal displayed items","location":{"column":24,"line":55,"path":"/home/runner/work/serenity-js-realworld-app-demo/serenity-js-realworld-app-demo/spec/recording_items.spec.ts"}},"outcome":{"code":64},"sceneId":"unknown","timestamp":"2024-04-29T21:31:51.630Z"}},{"type":"SceneFinishes","value":{"sceneId":"unknown","timestamp":"2024-04-29T21:31:51.641Z"}},{"type":"AsyncOperationAttempted","value":{"correlationId":"s355wpvjfsuxz9dcmd6up10q","description":"Dismissing Alice...","name":"Stage","timestamp":"2024-04-29T21:31:51.651Z"}},{"type":"AsyncOperationCompleted","value":{"correlationId":"s355wpvjfsuxz9dcmd6up10q","timestamp":"2024-04-29T21:31:51.651Z"}}]