[{"type":"SceneTagged","value":{"sceneId":"unknown","tag":{"name":"Linux 6.5.0-1018-azure","type":"platform","platformName":"Linux","platformVersion":"6.5.0-1018-azure"},"timestamp":"2024-05-08T16:43:53.178Z"}},{"type":"SceneTagged","value":{"sceneId":"unknown","tag":{"name":"chromium 121.0.6167.57","type":"browser","browserName":"chromium","browserVersion":"121.0.6167.57"},"timestamp":"2024-05-08T16:43:53.209Z"}},{"type":"TaskStarts","value":{"activityId":"enf4buouzygbfnmpftt72n33","details":{"name":"Alice starts with an empty todo list","location":{"column":37,"line":61,"path":"/home/runner/work/serenity-js-realworld-app-demo/serenity-js-realworld-app-demo/spec/recording_items.spec.ts"}},"sceneId":"unknown","timestamp":"2024-05-08T16:43:53.223Z"}},{"type":"InteractionStarts","value":{"activityId":"t43bsclznbgfjml8cxm47q4k","details":{"name":"Alice navigates to '/'","location":{"column":18,"line":9,"path":"/home/runner/work/serenity-js-realworld-app-demo/serenity-js-realworld-app-demo/spec/todo-list-app/TodoApp/tasks.ts"}},"sceneId":"unknown","timestamp":"2024-05-08T16:43:53.223Z"}},{"type":"InteractionFinished","value":{"activityId":"t43bsclznbgfjml8cxm47q4k","details":{"name":"Alice navigates to '/'","location":{"column":18,"line":9,"path":"/home/runner/work/serenity-js-realworld-app-demo/serenity-js-realworld-app-demo/spec/todo-list-app/TodoApp/tasks.ts"}},"outcome":{"code":64},"sceneId":"unknown","timestamp":"2024-05-08T16:43:53.443Z"}},{"type":"InteractionStarts","value":{"activityId":"opkg7jbxrm8wlfggq8c5jamw","details":{"name":"Alice ensures that website title does equal 'Serenity/JS TodoApp'","location":{"column":37,"line":61,"path":"/home/runner/work/serenity-js-realworld-app-demo/serenity-js-realworld-app-demo/spec/recording_items.spec.ts"}},"sceneId":"unknown","timestamp":"2024-05-08T16:43:53.454Z"}},{"type":"InteractionFinished","value":{"activityId":"opkg7jbxrm8wlfggq8c5jamw","details":{"name":"Alice ensures that website title does equal 'Serenity/JS TodoApp'","location":{"column":37,"line":61,"path":"/home/runner/work/serenity-js-realworld-app-demo/serenity-js-realworld-app-demo/spec/recording_items.spec.ts"}},"outcome":{"code":64},"sceneId":"unknown","timestamp":"2024-05-08T16:43:53.461Z"}},{"type":"TaskFinished","value":{"activityId":"enf4buouzygbfnmpftt72n33","details":{"name":"Alice starts with an empty todo list","location":{"column":37,"line":61,"path":"/home/runner/work/serenity-js-realworld-app-demo/serenity-js-realworld-app-demo/spec/recording_items.spec.ts"}},"outcome":{"code":64},"sceneId":"unknown","timestamp":"2024-05-08T16:43:53.471Z"}},{"type":"TaskStarts","value":{"activityId":"uwor3jcqfng9udltlyxr8xfj","details":{"name":"Alice records an item called 'buy some cheese'","location":{"column":27,"line":63,"path":"/home/runner/work/serenity-js-realworld-app-demo/serenity-js-realworld-app-demo/spec/recording_items.spec.ts"}},"sceneId":"unknown","timestamp":"2024-05-08T16:43:53.482Z"}},{"type":"InteractionStarts","value":{"activityId":"wt5gazwueru3hgt820qa45ew","details":{"name":"Alice enters 'buy some cheese' into \"What needs to be done?\" input box","location":{"column":30,"line":12,"path":"/home/runner/work/serenity-js-realworld-app-demo/serenity-js-realworld-app-demo/spec/todo-list-app/TodoItem/tasks.ts"}},"sceneId":"unknown","timestamp":"2024-05-08T16:43:53.483Z"}},{"type":"InteractionFinished","value":{"activityId":"wt5gazwueru3hgt820qa45ew","details":{"name":"Alice enters 'buy some cheese' into \"What needs to be done?\" input box","location":{"column":30,"line":12,"path":"/home/runner/work/serenity-js-realworld-app-demo/serenity-js-realworld-app-demo/spec/todo-list-app/TodoItem/tasks.ts"}},"outcome":{"code":64},"sceneId":"unknown","timestamp":"2024-05-08T16:43:53.507Z"}},{"type":"InteractionStarts","value":{"activityId":"yfqctvn7eklbtgksa0746c5w","details":{"name":"Alice presses key Enter in \"What needs to be done?\" input box","location":{"column":32,"line":13,"path":"/home/runner/work/serenity-js-realworld-app-demo/serenity-js-realworld-app-demo/spec/todo-list-app/TodoItem/tasks.ts"}},"sceneId":"unknown","timestamp":"2024-05-08T16:43:53.518Z"}},{"type":"InteractionFinished","value":{"activityId":"yfqctvn7eklbtgksa0746c5w","details":{"name":"Alice presses key Enter in \"What needs to be done?\" input box","location":{"column":32,"line":13,"path":"/home/runner/work/serenity-js-realworld-app-demo/serenity-js-realworld-app-demo/spec/todo-list-app/TodoItem/tasks.ts"}},"outcome":{"code":64},"sceneId":"unknown","timestamp":"2024-05-08T16:43:53.547Z"}},{"type":"InteractionStarts","value":{"activityId":"uqpw0ee8i3tqd9kq7wg0pc18","details":{"name":"Alice waits until displayed items does contain 'buy some cheese'","location":{"column":14,"line":14,"path":"/home/runner/work/serenity-js-realworld-app-demo/serenity-js-realworld-app-demo/spec/todo-list-app/TodoItem/tasks.ts"}},"sceneId":"unknown","timestamp":"2024-05-08T16:43:53.558Z"}},{"type":"InteractionFinished","value":{"activityId":"uqpw0ee8i3tqd9kq7wg0pc18","details":{"name":"Alice waits until displayed items does contain 'buy some cheese'","location":{"column":14,"line":14,"path":"/home/runner/work/serenity-js-realworld-app-demo/serenity-js-realworld-app-demo/spec/todo-list-app/TodoItem/tasks.ts"}},"outcome":{"code":64},"sceneId":"unknown","timestamp":"2024-05-08T16:43:53.575Z"}},{"type":"TaskFinished","value":{"activityId":"uwor3jcqfng9udltlyxr8xfj","details":{"name":"Alice records an item called 'buy some cheese'","location":{"column":27,"line":63,"path":"/home/runner/work/serenity-js-realworld-app-demo/serenity-js-realworld-app-demo/spec/recording_items.spec.ts"}},"outcome":{"code":64},"sceneId":"unknown","timestamp":"2024-05-08T16:43:53.585Z"}},{"type":"InteractionStarts","value":{"activityId":"qz737pbxnqnt3f59fwfrzsm8","details":{"name":"Alice ensures that the value of \"What needs to be done?\" input box does equal ''","location":{"column":24,"line":65,"path":"/home/runner/work/serenity-js-realworld-app-demo/serenity-js-realworld-app-demo/spec/recording_items.spec.ts"}},"sceneId":"unknown","timestamp":"2024-05-08T16:43:53.596Z"}},{"type":"InteractionFinished","value":{"activityId":"qz737pbxnqnt3f59fwfrzsm8","details":{"name":"Alice ensures that the value of \"What needs to be done?\" input box does equal ''","location":{"column":24,"line":65,"path":"/home/runner/work/serenity-js-realworld-app-demo/serenity-js-realworld-app-demo/spec/recording_items.spec.ts"}},"outcome":{"code":64},"sceneId":"unknown","timestamp":"2024-05-08T16:43:53.600Z"}},{"type":"InteractionStarts","value":{"activityId":"xni3woo8co6v4e9nf0dlxw8i","details":{"name":"Alice ensures that <<persisted item called buy some cheese>>.name does equal 'buy some cheese'","location":{"column":24,"line":67,"path":"/home/runner/work/serenity-js-realworld-app-demo/serenity-js-realworld-app-demo/spec/recording_items.spec.ts"}},"sceneId":"unknown","timestamp":"2024-05-08T16:43:53.611Z"}},{"type":"InteractionFinished","value":{"activityId":"xni3woo8co6v4e9nf0dlxw8i","details":{"name":"Alice ensures that <<persisted item called buy some cheese>>.name does equal 'buy some cheese'","location":{"column":24,"line":67,"path":"/home/runner/work/serenity-js-realworld-app-demo/serenity-js-realworld-app-demo/spec/recording_items.spec.ts"}},"outcome":{"code":64},"sceneId":"unknown","timestamp":"2024-05-08T16:43:53.615Z"}},{"type":"InteractionStarts","value":{"activityId":"be30d6pb2ya68iwlh1piwbyd","details":{"name":"Alice ensures that <<persisted item called buy some cheese>>.completed does equal false","location":{"column":24,"line":68,"path":"/home/runner/work/serenity-js-realworld-app-demo/serenity-js-realworld-app-demo/spec/recording_items.spec.ts"}},"sceneId":"unknown","timestamp":"2024-05-08T16:43:53.626Z"}},{"type":"InteractionFinished","value":{"activityId":"be30d6pb2ya68iwlh1piwbyd","details":{"name":"Alice ensures that <<persisted item called buy some cheese>>.completed does equal false","location":{"column":24,"line":68,"path":"/home/runner/work/serenity-js-realworld-app-demo/serenity-js-realworld-app-demo/spec/recording_items.spec.ts"}},"outcome":{"code":64},"sceneId":"unknown","timestamp":"2024-05-08T16:43:53.629Z"}},{"type":"SceneFinishes","value":{"sceneId":"unknown","timestamp":"2024-05-08T16:43:53.640Z"}},{"type":"AsyncOperationAttempted","value":{"correlationId":"tb0z2tygynnlj4jok6r7gnau","description":"Dismissing Alice...","name":"Stage","timestamp":"2024-05-08T16:43:53.650Z"}},{"type":"AsyncOperationCompleted","value":{"correlationId":"tb0z2tygynnlj4jok6r7gnau","timestamp":"2024-05-08T16:43:53.650Z"}}]