[{"type":"SceneTagged","value":{"sceneId":"unknown","tag":{"name":"Linux 6.5.0-1021-azure","type":"platform","platformName":"Linux","platformVersion":"6.5.0-1021-azure"},"timestamp":"2024-06-18T03:41:17.922Z"}},{"type":"SceneTagged","value":{"sceneId":"unknown","tag":{"name":"chromium 121.0.6167.57","type":"browser","browserName":"chromium","browserVersion":"121.0.6167.57"},"timestamp":"2024-06-18T03:41:17.923Z"}},{"type":"TaskStarts","value":{"activityId":"axc360o8t28hlsoj242znp1s","details":{"name":"Alice starts with a list containing 1 items","location":{"column":41,"line":39,"path":"/home/runner/work/serenity-js-realworld-app-demo/serenity-js-realworld-app-demo/spec/multi-actor_scenarios.spec.ts"}},"sceneId":"unknown","timestamp":"2024-06-18T03:41:17.931Z"}},{"type":"TaskStarts","value":{"activityId":"lyut6zxapyoytpqsgdiqjz93","details":{"name":"Alice starts with an empty todo list","location":{"column":9,"line":18,"path":"/home/runner/work/serenity-js-realworld-app-demo/serenity-js-realworld-app-demo/spec/todo-list-app/TodoApp/tasks.ts"}},"sceneId":"unknown","timestamp":"2024-06-18T03:41:17.932Z"}},{"type":"InteractionStarts","value":{"activityId":"wiqz3t6qxow5n0m2lj5zqfff","details":{"name":"Alice navigates to '/'","location":{"column":18,"line":9,"path":"/home/runner/work/serenity-js-realworld-app-demo/serenity-js-realworld-app-demo/spec/todo-list-app/TodoApp/tasks.ts"}},"sceneId":"unknown","timestamp":"2024-06-18T03:41:17.932Z"}},{"type":"InteractionFinished","value":{"activityId":"wiqz3t6qxow5n0m2lj5zqfff","details":{"name":"Alice navigates to '/'","location":{"column":18,"line":9,"path":"/home/runner/work/serenity-js-realworld-app-demo/serenity-js-realworld-app-demo/spec/todo-list-app/TodoApp/tasks.ts"}},"outcome":{"code":64},"sceneId":"unknown","timestamp":"2024-06-18T03:41:18.090Z"}},{"type":"InteractionStarts","value":{"activityId":"kyhk61ryboq1z6xtd3az45sm","details":{"name":"Alice ensures that website title does equal 'Serenity/JS TodoApp'","location":{"column":41,"line":39,"path":"/home/runner/work/serenity-js-realworld-app-demo/serenity-js-realworld-app-demo/spec/multi-actor_scenarios.spec.ts"}},"sceneId":"unknown","timestamp":"2024-06-18T03:41:18.101Z"}},{"type":"InteractionFinished","value":{"activityId":"kyhk61ryboq1z6xtd3az45sm","details":{"name":"Alice ensures that website title does equal 'Serenity/JS TodoApp'","location":{"column":41,"line":39,"path":"/home/runner/work/serenity-js-realworld-app-demo/serenity-js-realworld-app-demo/spec/multi-actor_scenarios.spec.ts"}},"outcome":{"code":64},"sceneId":"unknown","timestamp":"2024-06-18T03:41:18.108Z"}},{"type":"TaskFinished","value":{"activityId":"lyut6zxapyoytpqsgdiqjz93","details":{"name":"Alice starts with an empty todo list","location":{"column":9,"line":18,"path":"/home/runner/work/serenity-js-realworld-app-demo/serenity-js-realworld-app-demo/spec/todo-list-app/TodoApp/tasks.ts"}},"outcome":{"code":64},"sceneId":"unknown","timestamp":"2024-06-18T03:41:18.118Z"}},{"type":"TaskStarts","value":{"activityId":"rnjvqv9nj9oeqw2xesplw9w4","details":{"name":"Alice records an item called 'Feed the cat'","location":{"column":18,"line":19,"path":"/home/runner/work/serenity-js-realworld-app-demo/serenity-js-realworld-app-demo/spec/todo-list-app/TodoApp/tasks.ts"}},"sceneId":"unknown","timestamp":"2024-06-18T03:41:18.129Z"}},{"type":"InteractionStarts","value":{"activityId":"goxo3427awovqlnzec5l2tfy","details":{"name":"Alice enters 'Feed the cat' into \"What needs to be done?\" input box","location":{"column":30,"line":12,"path":"/home/runner/work/serenity-js-realworld-app-demo/serenity-js-realworld-app-demo/spec/todo-list-app/TodoItem/tasks.ts"}},"sceneId":"unknown","timestamp":"2024-06-18T03:41:18.130Z"}},{"type":"InteractionFinished","value":{"activityId":"goxo3427awovqlnzec5l2tfy","details":{"name":"Alice enters 'Feed the cat' into \"What needs to be done?\" input box","location":{"column":30,"line":12,"path":"/home/runner/work/serenity-js-realworld-app-demo/serenity-js-realworld-app-demo/spec/todo-list-app/TodoItem/tasks.ts"}},"outcome":{"code":64},"sceneId":"unknown","timestamp":"2024-06-18T03:41:18.167Z"}},{"type":"InteractionStarts","value":{"activityId":"uy1qy7tofx4dgu5ojeir79wu","details":{"name":"Alice presses key Enter in \"What needs to be done?\" input box","location":{"column":32,"line":13,"path":"/home/runner/work/serenity-js-realworld-app-demo/serenity-js-realworld-app-demo/spec/todo-list-app/TodoItem/tasks.ts"}},"sceneId":"unknown","timestamp":"2024-06-18T03:41:18.179Z"}},{"type":"InteractionFinished","value":{"activityId":"uy1qy7tofx4dgu5ojeir79wu","details":{"name":"Alice presses key Enter in \"What needs to be done?\" input box","location":{"column":32,"line":13,"path":"/home/runner/work/serenity-js-realworld-app-demo/serenity-js-realworld-app-demo/spec/todo-list-app/TodoItem/tasks.ts"}},"outcome":{"code":64},"sceneId":"unknown","timestamp":"2024-06-18T03:41:18.212Z"}},{"type":"InteractionStarts","value":{"activityId":"pja388xkddaogeoufd7twmbd","details":{"name":"Alice waits until displayed items does contain 'Feed the cat'","location":{"column":14,"line":14,"path":"/home/runner/work/serenity-js-realworld-app-demo/serenity-js-realworld-app-demo/spec/todo-list-app/TodoItem/tasks.ts"}},"sceneId":"unknown","timestamp":"2024-06-18T03:41:18.224Z"}},{"type":"InteractionFinished","value":{"activityId":"pja388xkddaogeoufd7twmbd","details":{"name":"Alice waits until displayed items does contain 'Feed the cat'","location":{"column":14,"line":14,"path":"/home/runner/work/serenity-js-realworld-app-demo/serenity-js-realworld-app-demo/spec/todo-list-app/TodoItem/tasks.ts"}},"outcome":{"code":64},"sceneId":"unknown","timestamp":"2024-06-18T03:41:18.243Z"}},{"type":"TaskFinished","value":{"activityId":"rnjvqv9nj9oeqw2xesplw9w4","details":{"name":"Alice records an item called 'Feed the cat'","location":{"column":18,"line":19,"path":"/home/runner/work/serenity-js-realworld-app-demo/serenity-js-realworld-app-demo/spec/todo-list-app/TodoApp/tasks.ts"}},"outcome":{"code":64},"sceneId":"unknown","timestamp":"2024-06-18T03:41:18.253Z"}},{"type":"TaskFinished","value":{"activityId":"axc360o8t28hlsoj242znp1s","details":{"name":"Alice starts with a list containing 1 items","location":{"column":41,"line":39,"path":"/home/runner/work/serenity-js-realworld-app-demo/serenity-js-realworld-app-demo/spec/multi-actor_scenarios.spec.ts"}},"outcome":{"code":64},"sceneId":"unknown","timestamp":"2024-06-18T03:41:18.264Z"}},{"type":"TaskStarts","value":{"activityId":"nswe2j8p41feceh02xevvty8","details":{"name":"Bob starts with a list containing 1 items","location":{"column":41,"line":45,"path":"/home/runner/work/serenity-js-realworld-app-demo/serenity-js-realworld-app-demo/spec/multi-actor_scenarios.spec.ts"}},"sceneId":"unknown","timestamp":"2024-06-18T03:41:18.284Z"}},{"type":"TaskStarts","value":{"activityId":"c76imf32z0xk6cjig1mli7gs","details":{"name":"Bob starts with an empty todo list","location":{"column":9,"line":18,"path":"/home/runner/work/serenity-js-realworld-app-demo/serenity-js-realworld-app-demo/spec/todo-list-app/TodoApp/tasks.ts"}},"sceneId":"unknown","timestamp":"2024-06-18T03:41:18.285Z"}},{"type":"InteractionStarts","value":{"activityId":"pp1wwtjj3zus5pbeda65fqvq","details":{"name":"Bob navigates to '/'","location":{"column":18,"line":9,"path":"/home/runner/work/serenity-js-realworld-app-demo/serenity-js-realworld-app-demo/spec/todo-list-app/TodoApp/tasks.ts"}},"sceneId":"unknown","timestamp":"2024-06-18T03:41:18.285Z"}},{"type":"InteractionFinished","value":{"activityId":"pp1wwtjj3zus5pbeda65fqvq","details":{"name":"Bob navigates to '/'","location":{"column":18,"line":9,"path":"/home/runner/work/serenity-js-realworld-app-demo/serenity-js-realworld-app-demo/spec/todo-list-app/TodoApp/tasks.ts"}},"outcome":{"code":64},"sceneId":"unknown","timestamp":"2024-06-18T03:41:18.494Z"}},{"type":"InteractionStarts","value":{"activityId":"jh8webp4jakp3l5vgcmhdwwv","details":{"name":"Bob ensures that website title does equal 'Serenity/JS TodoApp'","location":{"column":41,"line":45,"path":"/home/runner/work/serenity-js-realworld-app-demo/serenity-js-realworld-app-demo/spec/multi-actor_scenarios.spec.ts"}},"sceneId":"unknown","timestamp":"2024-06-18T03:41:18.506Z"}},{"type":"InteractionFinished","value":{"activityId":"jh8webp4jakp3l5vgcmhdwwv","details":{"name":"Bob ensures that website title does equal 'Serenity/JS TodoApp'","location":{"column":41,"line":45,"path":"/home/runner/work/serenity-js-realworld-app-demo/serenity-js-realworld-app-demo/spec/multi-actor_scenarios.spec.ts"}},"outcome":{"code":64},"sceneId":"unknown","timestamp":"2024-06-18T03:41:18.512Z"}},{"type":"TaskFinished","value":{"activityId":"c76imf32z0xk6cjig1mli7gs","details":{"name":"Bob starts with an empty todo list","location":{"column":9,"line":18,"path":"/home/runner/work/serenity-js-realworld-app-demo/serenity-js-realworld-app-demo/spec/todo-list-app/TodoApp/tasks.ts"}},"outcome":{"code":64},"sceneId":"unknown","timestamp":"2024-06-18T03:41:18.521Z"}},{"type":"TaskStarts","value":{"activityId":"frp2k4ekj2530dr9n62so1fx","details":{"name":"Bob records an item called 'Walk the dog'","location":{"column":18,"line":19,"path":"/home/runner/work/serenity-js-realworld-app-demo/serenity-js-realworld-app-demo/spec/todo-list-app/TodoApp/tasks.ts"}},"sceneId":"unknown","timestamp":"2024-06-18T03:41:18.532Z"}},{"type":"InteractionStarts","value":{"activityId":"ehtnbyph49qpi8d2ccd3czmj","details":{"name":"Bob enters 'Walk the dog' into \"What needs to be done?\" input box","location":{"column":30,"line":12,"path":"/home/runner/work/serenity-js-realworld-app-demo/serenity-js-realworld-app-demo/spec/todo-list-app/TodoItem/tasks.ts"}},"sceneId":"unknown","timestamp":"2024-06-18T03:41:18.532Z"}},{"type":"InteractionFinished","value":{"activityId":"ehtnbyph49qpi8d2ccd3czmj","details":{"name":"Bob enters 'Walk the dog' into \"What needs to be done?\" input box","location":{"column":30,"line":12,"path":"/home/runner/work/serenity-js-realworld-app-demo/serenity-js-realworld-app-demo/spec/todo-list-app/TodoItem/tasks.ts"}},"outcome":{"code":64},"sceneId":"unknown","timestamp":"2024-06-18T03:41:18.557Z"}},{"type":"InteractionStarts","value":{"activityId":"zocn6lc7r3v8q8f2vhnbfmkb","details":{"name":"Bob presses key Enter in \"What needs to be done?\" input box","location":{"column":32,"line":13,"path":"/home/runner/work/serenity-js-realworld-app-demo/serenity-js-realworld-app-demo/spec/todo-list-app/TodoItem/tasks.ts"}},"sceneId":"unknown","timestamp":"2024-06-18T03:41:18.568Z"}},{"type":"InteractionFinished","value":{"activityId":"zocn6lc7r3v8q8f2vhnbfmkb","details":{"name":"Bob presses key Enter in \"What needs to be done?\" input box","location":{"column":32,"line":13,"path":"/home/runner/work/serenity-js-realworld-app-demo/serenity-js-realworld-app-demo/spec/todo-list-app/TodoItem/tasks.ts"}},"outcome":{"code":64},"sceneId":"unknown","timestamp":"2024-06-18T03:41:18.593Z"}},{"type":"InteractionStarts","value":{"activityId":"rgxakef8yufpftr5mb7b954a","details":{"name":"Bob waits until displayed items does contain 'Walk the dog'","location":{"column":14,"line":14,"path":"/home/runner/work/serenity-js-realworld-app-demo/serenity-js-realworld-app-demo/spec/todo-list-app/TodoItem/tasks.ts"}},"sceneId":"unknown","timestamp":"2024-06-18T03:41:18.604Z"}},{"type":"InteractionFinished","value":{"activityId":"rgxakef8yufpftr5mb7b954a","details":{"name":"Bob waits until displayed items does contain 'Walk the dog'","location":{"column":14,"line":14,"path":"/home/runner/work/serenity-js-realworld-app-demo/serenity-js-realworld-app-demo/spec/todo-list-app/TodoItem/tasks.ts"}},"outcome":{"code":64},"sceneId":"unknown","timestamp":"2024-06-18T03:41:18.622Z"}},{"type":"TaskFinished","value":{"activityId":"frp2k4ekj2530dr9n62so1fx","details":{"name":"Bob records an item called 'Walk the dog'","location":{"column":18,"line":19,"path":"/home/runner/work/serenity-js-realworld-app-demo/serenity-js-realworld-app-demo/spec/todo-list-app/TodoApp/tasks.ts"}},"outcome":{"code":64},"sceneId":"unknown","timestamp":"2024-06-18T03:41:18.632Z"}},{"type":"TaskFinished","value":{"activityId":"nswe2j8p41feceh02xevvty8","details":{"name":"Bob starts with a list containing 1 items","location":{"column":41,"line":45,"path":"/home/runner/work/serenity-js-realworld-app-demo/serenity-js-realworld-app-demo/spec/multi-actor_scenarios.spec.ts"}},"outcome":{"code":64},"sceneId":"unknown","timestamp":"2024-06-18T03:41:18.642Z"}},{"type":"InteractionStarts","value":{"activityId":"y5beji716c23rojqrevvw2x7","details":{"name":"Alice ensures that displayed items does equal [ 'Feed the cat' ]","location":{"column":24,"line":51,"path":"/home/runner/work/serenity-js-realworld-app-demo/serenity-js-realworld-app-demo/spec/multi-actor_scenarios.spec.ts"}},"sceneId":"unknown","timestamp":"2024-06-18T03:41:18.655Z"}},{"type":"InteractionFinished","value":{"activityId":"y5beji716c23rojqrevvw2x7","details":{"name":"Alice ensures that displayed items does equal [ 'Feed the cat' ]","location":{"column":24,"line":51,"path":"/home/runner/work/serenity-js-realworld-app-demo/serenity-js-realworld-app-demo/spec/multi-actor_scenarios.spec.ts"}},"outcome":{"code":64},"sceneId":"unknown","timestamp":"2024-06-18T03:41:18.662Z"}},{"type":"InteractionStarts","value":{"activityId":"eh71lyy49em8srh22ez6d46m","details":{"name":"Bob ensures that displayed items does equal [ 'Walk the dog' ]","location":{"column":24,"line":57,"path":"/home/runner/work/serenity-js-realworld-app-demo/serenity-js-realworld-app-demo/spec/multi-actor_scenarios.spec.ts"}},"sceneId":"unknown","timestamp":"2024-06-18T03:41:18.675Z"}},{"type":"InteractionFinished","value":{"activityId":"eh71lyy49em8srh22ez6d46m","details":{"name":"Bob ensures that displayed items does equal [ 'Walk the dog' ]","location":{"column":24,"line":57,"path":"/home/runner/work/serenity-js-realworld-app-demo/serenity-js-realworld-app-demo/spec/multi-actor_scenarios.spec.ts"}},"outcome":{"code":64},"sceneId":"unknown","timestamp":"2024-06-18T03:41:18.682Z"}},{"type":"SceneFinishes","value":{"sceneId":"unknown","timestamp":"2024-06-18T03:41:18.692Z"}},{"type":"AsyncOperationAttempted","value":{"correlationId":"bqe1cui9d6nf5aa8wfzvis5x","description":"Dismissing Alice...","name":"Stage","timestamp":"2024-06-18T03:41:18.703Z"}},{"type":"AsyncOperationAttempted","value":{"correlationId":"won56t3jdoo99f1my8rwkov9","description":"Dismissing Bob...","name":"Stage","timestamp":"2024-06-18T03:41:18.703Z"}},{"type":"AsyncOperationCompleted","value":{"correlationId":"bqe1cui9d6nf5aa8wfzvis5x","timestamp":"2024-06-18T03:41:18.710Z"}},{"type":"AsyncOperationCompleted","value":{"correlationId":"won56t3jdoo99f1my8rwkov9","timestamp":"2024-06-18T03:41:18.716Z"}}]