[{"type":"SceneTagged","value":{"sceneId":"unknown","tag":{"name":"Linux 6.5.0-1023-azure","type":"platform","platformName":"Linux","platformVersion":"6.5.0-1023-azure"},"timestamp":"2024-07-17T02:18:35.598Z"}},{"type":"SceneTagged","value":{"sceneId":"unknown","tag":{"name":"webkit 17.4","type":"browser","browserName":"webkit","browserVersion":"17.4"},"timestamp":"2024-07-17T02:18:35.599Z"}},{"type":"TaskStarts","value":{"activityId":"at2ap7c5xcz4grzrl0ngw57t","details":{"name":"Alice starts with a list containing 1 items","location":{"column":41,"line":39,"path":"/home/runner/work/serenity-js-realworld-app-demo/serenity-js-realworld-app-demo/spec/multi-actor_scenarios.spec.ts"}},"sceneId":"unknown","timestamp":"2024-07-17T02:18:35.609Z"}},{"type":"TaskStarts","value":{"activityId":"isb00frlky5q9l32v88ioqbq","details":{"name":"Alice starts with an empty todo list","location":{"column":9,"line":18,"path":"/home/runner/work/serenity-js-realworld-app-demo/serenity-js-realworld-app-demo/spec/todo-list-app/TodoApp/tasks.ts"}},"sceneId":"unknown","timestamp":"2024-07-17T02:18:35.610Z"}},{"type":"InteractionStarts","value":{"activityId":"jqz5zyr46avtqh9oueoyewlc","details":{"name":"Alice navigates to '/'","location":{"column":18,"line":9,"path":"/home/runner/work/serenity-js-realworld-app-demo/serenity-js-realworld-app-demo/spec/todo-list-app/TodoApp/tasks.ts"}},"sceneId":"unknown","timestamp":"2024-07-17T02:18:35.610Z"}},{"type":"InteractionFinished","value":{"activityId":"jqz5zyr46avtqh9oueoyewlc","details":{"name":"Alice navigates to '/'","location":{"column":18,"line":9,"path":"/home/runner/work/serenity-js-realworld-app-demo/serenity-js-realworld-app-demo/spec/todo-list-app/TodoApp/tasks.ts"}},"outcome":{"code":64},"sceneId":"unknown","timestamp":"2024-07-17T02:18:36.020Z"}},{"type":"InteractionStarts","value":{"activityId":"xuh700f2ozt4owd2b16xksf8","details":{"name":"Alice ensures that website title does equal 'Serenity/JS TodoApp'","location":{"column":41,"line":39,"path":"/home/runner/work/serenity-js-realworld-app-demo/serenity-js-realworld-app-demo/spec/multi-actor_scenarios.spec.ts"}},"sceneId":"unknown","timestamp":"2024-07-17T02:18:36.032Z"}},{"type":"InteractionFinished","value":{"activityId":"xuh700f2ozt4owd2b16xksf8","details":{"name":"Alice ensures that website title does equal 'Serenity/JS TodoApp'","location":{"column":41,"line":39,"path":"/home/runner/work/serenity-js-realworld-app-demo/serenity-js-realworld-app-demo/spec/multi-actor_scenarios.spec.ts"}},"outcome":{"code":64},"sceneId":"unknown","timestamp":"2024-07-17T02:18:36.040Z"}},{"type":"TaskFinished","value":{"activityId":"isb00frlky5q9l32v88ioqbq","details":{"name":"Alice starts with an empty todo list","location":{"column":9,"line":18,"path":"/home/runner/work/serenity-js-realworld-app-demo/serenity-js-realworld-app-demo/spec/todo-list-app/TodoApp/tasks.ts"}},"outcome":{"code":64},"sceneId":"unknown","timestamp":"2024-07-17T02:18:36.050Z"}},{"type":"TaskStarts","value":{"activityId":"p67jv6fw7lwxj3vcyoc9uvvm","details":{"name":"Alice records an item called 'Feed the cat'","location":{"column":18,"line":19,"path":"/home/runner/work/serenity-js-realworld-app-demo/serenity-js-realworld-app-demo/spec/todo-list-app/TodoApp/tasks.ts"}},"sceneId":"unknown","timestamp":"2024-07-17T02:18:36.062Z"}},{"type":"InteractionStarts","value":{"activityId":"c1np4mnds76yjki6n68gco6u","details":{"name":"Alice enters 'Feed the cat' into \"What needs to be done?\" input box","location":{"column":30,"line":12,"path":"/home/runner/work/serenity-js-realworld-app-demo/serenity-js-realworld-app-demo/spec/todo-list-app/TodoItem/tasks.ts"}},"sceneId":"unknown","timestamp":"2024-07-17T02:18:36.062Z"}},{"type":"InteractionFinished","value":{"activityId":"c1np4mnds76yjki6n68gco6u","details":{"name":"Alice enters 'Feed the cat' into \"What needs to be done?\" input box","location":{"column":30,"line":12,"path":"/home/runner/work/serenity-js-realworld-app-demo/serenity-js-realworld-app-demo/spec/todo-list-app/TodoItem/tasks.ts"}},"outcome":{"code":64},"sceneId":"unknown","timestamp":"2024-07-17T02:18:36.093Z"}},{"type":"InteractionStarts","value":{"activityId":"s8aud75koqvwpclannu8ujtn","details":{"name":"Alice presses key Enter in \"What needs to be done?\" input box","location":{"column":32,"line":13,"path":"/home/runner/work/serenity-js-realworld-app-demo/serenity-js-realworld-app-demo/spec/todo-list-app/TodoItem/tasks.ts"}},"sceneId":"unknown","timestamp":"2024-07-17T02:18:36.104Z"}},{"type":"InteractionFinished","value":{"activityId":"s8aud75koqvwpclannu8ujtn","details":{"name":"Alice presses key Enter in \"What needs to be done?\" input box","location":{"column":32,"line":13,"path":"/home/runner/work/serenity-js-realworld-app-demo/serenity-js-realworld-app-demo/spec/todo-list-app/TodoItem/tasks.ts"}},"outcome":{"code":64},"sceneId":"unknown","timestamp":"2024-07-17T02:18:36.171Z"}},{"type":"InteractionStarts","value":{"activityId":"s1ie1nxu9gk0iap9t4m41unr","details":{"name":"Alice waits until displayed items does contain 'Feed the cat'","location":{"column":14,"line":14,"path":"/home/runner/work/serenity-js-realworld-app-demo/serenity-js-realworld-app-demo/spec/todo-list-app/TodoItem/tasks.ts"}},"sceneId":"unknown","timestamp":"2024-07-17T02:18:36.182Z"}},{"type":"InteractionFinished","value":{"activityId":"s1ie1nxu9gk0iap9t4m41unr","details":{"name":"Alice waits until displayed items does contain 'Feed the cat'","location":{"column":14,"line":14,"path":"/home/runner/work/serenity-js-realworld-app-demo/serenity-js-realworld-app-demo/spec/todo-list-app/TodoItem/tasks.ts"}},"outcome":{"code":64},"sceneId":"unknown","timestamp":"2024-07-17T02:18:36.208Z"}},{"type":"TaskFinished","value":{"activityId":"p67jv6fw7lwxj3vcyoc9uvvm","details":{"name":"Alice records an item called 'Feed the cat'","location":{"column":18,"line":19,"path":"/home/runner/work/serenity-js-realworld-app-demo/serenity-js-realworld-app-demo/spec/todo-list-app/TodoApp/tasks.ts"}},"outcome":{"code":64},"sceneId":"unknown","timestamp":"2024-07-17T02:18:36.218Z"}},{"type":"TaskFinished","value":{"activityId":"at2ap7c5xcz4grzrl0ngw57t","details":{"name":"Alice starts with a list containing 1 items","location":{"column":41,"line":39,"path":"/home/runner/work/serenity-js-realworld-app-demo/serenity-js-realworld-app-demo/spec/multi-actor_scenarios.spec.ts"}},"outcome":{"code":64},"sceneId":"unknown","timestamp":"2024-07-17T02:18:36.229Z"}},{"type":"TaskStarts","value":{"activityId":"g1bybj7w9t7l29yixxd08i66","details":{"name":"Bob starts with a list containing 1 items","location":{"column":41,"line":45,"path":"/home/runner/work/serenity-js-realworld-app-demo/serenity-js-realworld-app-demo/spec/multi-actor_scenarios.spec.ts"}},"sceneId":"unknown","timestamp":"2024-07-17T02:18:36.250Z"}},{"type":"TaskStarts","value":{"activityId":"rn0rbw7yzej3fwg9xcrdhoso","details":{"name":"Bob starts with an empty todo list","location":{"column":9,"line":18,"path":"/home/runner/work/serenity-js-realworld-app-demo/serenity-js-realworld-app-demo/spec/todo-list-app/TodoApp/tasks.ts"}},"sceneId":"unknown","timestamp":"2024-07-17T02:18:36.251Z"}},{"type":"InteractionStarts","value":{"activityId":"siuaxuvjtti8vy53bq5awx4t","details":{"name":"Bob navigates to '/'","location":{"column":18,"line":9,"path":"/home/runner/work/serenity-js-realworld-app-demo/serenity-js-realworld-app-demo/spec/todo-list-app/TodoApp/tasks.ts"}},"sceneId":"unknown","timestamp":"2024-07-17T02:18:36.251Z"}},{"type":"InteractionFinished","value":{"activityId":"siuaxuvjtti8vy53bq5awx4t","details":{"name":"Bob navigates to '/'","location":{"column":18,"line":9,"path":"/home/runner/work/serenity-js-realworld-app-demo/serenity-js-realworld-app-demo/spec/todo-list-app/TodoApp/tasks.ts"}},"outcome":{"code":64},"sceneId":"unknown","timestamp":"2024-07-17T02:18:36.674Z"}},{"type":"InteractionStarts","value":{"activityId":"q9pnvfwfgm4vjtjbn5w9abto","details":{"name":"Bob ensures that website title does equal 'Serenity/JS TodoApp'","location":{"column":41,"line":45,"path":"/home/runner/work/serenity-js-realworld-app-demo/serenity-js-realworld-app-demo/spec/multi-actor_scenarios.spec.ts"}},"sceneId":"unknown","timestamp":"2024-07-17T02:18:36.685Z"}},{"type":"InteractionFinished","value":{"activityId":"q9pnvfwfgm4vjtjbn5w9abto","details":{"name":"Bob ensures that website title does equal 'Serenity/JS TodoApp'","location":{"column":41,"line":45,"path":"/home/runner/work/serenity-js-realworld-app-demo/serenity-js-realworld-app-demo/spec/multi-actor_scenarios.spec.ts"}},"outcome":{"code":64},"sceneId":"unknown","timestamp":"2024-07-17T02:18:36.695Z"}},{"type":"TaskFinished","value":{"activityId":"rn0rbw7yzej3fwg9xcrdhoso","details":{"name":"Bob starts with an empty todo list","location":{"column":9,"line":18,"path":"/home/runner/work/serenity-js-realworld-app-demo/serenity-js-realworld-app-demo/spec/todo-list-app/TodoApp/tasks.ts"}},"outcome":{"code":64},"sceneId":"unknown","timestamp":"2024-07-17T02:18:36.705Z"}},{"type":"TaskStarts","value":{"activityId":"khn9fe81y4jj331dfmknuxiv","details":{"name":"Bob records an item called 'Walk the dog'","location":{"column":18,"line":19,"path":"/home/runner/work/serenity-js-realworld-app-demo/serenity-js-realworld-app-demo/spec/todo-list-app/TodoApp/tasks.ts"}},"sceneId":"unknown","timestamp":"2024-07-17T02:18:36.715Z"}},{"type":"InteractionStarts","value":{"activityId":"iroden09mhszxwgoqm3k2bla","details":{"name":"Bob enters 'Walk the dog' into \"What needs to be done?\" input box","location":{"column":30,"line":12,"path":"/home/runner/work/serenity-js-realworld-app-demo/serenity-js-realworld-app-demo/spec/todo-list-app/TodoItem/tasks.ts"}},"sceneId":"unknown","timestamp":"2024-07-17T02:18:36.716Z"}},{"type":"InteractionFinished","value":{"activityId":"iroden09mhszxwgoqm3k2bla","details":{"name":"Bob enters 'Walk the dog' into \"What needs to be done?\" input box","location":{"column":30,"line":12,"path":"/home/runner/work/serenity-js-realworld-app-demo/serenity-js-realworld-app-demo/spec/todo-list-app/TodoItem/tasks.ts"}},"outcome":{"code":64},"sceneId":"unknown","timestamp":"2024-07-17T02:18:36.752Z"}},{"type":"InteractionStarts","value":{"activityId":"g8fadh830veesyo1cieov5o5","details":{"name":"Bob presses key Enter in \"What needs to be done?\" input box","location":{"column":32,"line":13,"path":"/home/runner/work/serenity-js-realworld-app-demo/serenity-js-realworld-app-demo/spec/todo-list-app/TodoItem/tasks.ts"}},"sceneId":"unknown","timestamp":"2024-07-17T02:18:36.774Z"}},{"type":"InteractionFinished","value":{"activityId":"g8fadh830veesyo1cieov5o5","details":{"name":"Bob presses key Enter in \"What needs to be done?\" input box","location":{"column":32,"line":13,"path":"/home/runner/work/serenity-js-realworld-app-demo/serenity-js-realworld-app-demo/spec/todo-list-app/TodoItem/tasks.ts"}},"outcome":{"code":64},"sceneId":"unknown","timestamp":"2024-07-17T02:18:36.814Z"}},{"type":"InteractionStarts","value":{"activityId":"qegidmtsn8xsqrph84ymengx","details":{"name":"Bob waits until displayed items does contain 'Walk the dog'","location":{"column":14,"line":14,"path":"/home/runner/work/serenity-js-realworld-app-demo/serenity-js-realworld-app-demo/spec/todo-list-app/TodoItem/tasks.ts"}},"sceneId":"unknown","timestamp":"2024-07-17T02:18:36.825Z"}},{"type":"InteractionFinished","value":{"activityId":"qegidmtsn8xsqrph84ymengx","details":{"name":"Bob waits until displayed items does contain 'Walk the dog'","location":{"column":14,"line":14,"path":"/home/runner/work/serenity-js-realworld-app-demo/serenity-js-realworld-app-demo/spec/todo-list-app/TodoItem/tasks.ts"}},"outcome":{"code":64},"sceneId":"unknown","timestamp":"2024-07-17T02:18:36.848Z"}},{"type":"TaskFinished","value":{"activityId":"khn9fe81y4jj331dfmknuxiv","details":{"name":"Bob records an item called 'Walk the dog'","location":{"column":18,"line":19,"path":"/home/runner/work/serenity-js-realworld-app-demo/serenity-js-realworld-app-demo/spec/todo-list-app/TodoApp/tasks.ts"}},"outcome":{"code":64},"sceneId":"unknown","timestamp":"2024-07-17T02:18:36.864Z"}},{"type":"TaskFinished","value":{"activityId":"g1bybj7w9t7l29yixxd08i66","details":{"name":"Bob starts with a list containing 1 items","location":{"column":41,"line":45,"path":"/home/runner/work/serenity-js-realworld-app-demo/serenity-js-realworld-app-demo/spec/multi-actor_scenarios.spec.ts"}},"outcome":{"code":64},"sceneId":"unknown","timestamp":"2024-07-17T02:18:36.874Z"}},{"type":"InteractionStarts","value":{"activityId":"gal3jbsv0drw7nlxuzsjwrmu","details":{"name":"Alice ensures that displayed items does equal [ 'Feed the cat' ]","location":{"column":24,"line":51,"path":"/home/runner/work/serenity-js-realworld-app-demo/serenity-js-realworld-app-demo/spec/multi-actor_scenarios.spec.ts"}},"sceneId":"unknown","timestamp":"2024-07-17T02:18:36.887Z"}},{"type":"InteractionFinished","value":{"activityId":"gal3jbsv0drw7nlxuzsjwrmu","details":{"name":"Alice ensures that displayed items does equal [ 'Feed the cat' ]","location":{"column":24,"line":51,"path":"/home/runner/work/serenity-js-realworld-app-demo/serenity-js-realworld-app-demo/spec/multi-actor_scenarios.spec.ts"}},"outcome":{"code":64},"sceneId":"unknown","timestamp":"2024-07-17T02:18:36.894Z"}},{"type":"InteractionStarts","value":{"activityId":"aac7972t14hr37i4v8o5v5my","details":{"name":"Bob ensures that displayed items does equal [ 'Walk the dog' ]","location":{"column":24,"line":57,"path":"/home/runner/work/serenity-js-realworld-app-demo/serenity-js-realworld-app-demo/spec/multi-actor_scenarios.spec.ts"}},"sceneId":"unknown","timestamp":"2024-07-17T02:18:36.907Z"}},{"type":"InteractionFinished","value":{"activityId":"aac7972t14hr37i4v8o5v5my","details":{"name":"Bob ensures that displayed items does equal [ 'Walk the dog' ]","location":{"column":24,"line":57,"path":"/home/runner/work/serenity-js-realworld-app-demo/serenity-js-realworld-app-demo/spec/multi-actor_scenarios.spec.ts"}},"outcome":{"code":64},"sceneId":"unknown","timestamp":"2024-07-17T02:18:36.913Z"}},{"type":"SceneFinishes","value":{"sceneId":"unknown","timestamp":"2024-07-17T02:18:36.925Z"}},{"type":"AsyncOperationAttempted","value":{"correlationId":"k1g7i9x2buq297r13dil81ow","description":"Dismissing Alice...","name":"Stage","timestamp":"2024-07-17T02:18:36.935Z"}},{"type":"AsyncOperationAttempted","value":{"correlationId":"fb7k5qdmgl9jvvnnjmdebjg4","description":"Dismissing Bob...","name":"Stage","timestamp":"2024-07-17T02:18:36.935Z"}},{"type":"AsyncOperationCompleted","value":{"correlationId":"k1g7i9x2buq297r13dil81ow","timestamp":"2024-07-17T02:18:36.940Z"}},{"type":"AsyncOperationCompleted","value":{"correlationId":"fb7k5qdmgl9jvvnnjmdebjg4","timestamp":"2024-07-17T02:18:36.953Z"}}]