[{"type":"SceneTagged","value":{"sceneId":"unknown","tag":{"name":"Linux 6.5.0-1021-azure","type":"platform","platformName":"Linux","platformVersion":"6.5.0-1021-azure"},"timestamp":"2024-06-17T21:13:26.819Z"}},{"type":"SceneTagged","value":{"sceneId":"unknown","tag":{"name":"chromium 121.0.6167.57","type":"browser","browserName":"chromium","browserVersion":"121.0.6167.57"},"timestamp":"2024-06-17T21:13:26.854Z"}},{"type":"TaskStarts","value":{"activityId":"tjky3dgtomj6jxzzd7j51dm8","details":{"name":"Alice starts with an empty todo list","location":{"column":37,"line":83,"path":"/home/runner/work/serenity-js-realworld-app-demo/serenity-js-realworld-app-demo/spec/recording_items.spec.ts"}},"sceneId":"unknown","timestamp":"2024-06-17T21:13:26.866Z"}},{"type":"InteractionStarts","value":{"activityId":"c1mtitouh4atvzkibc2v08se","details":{"name":"Alice navigates to '/'","location":{"column":18,"line":9,"path":"/home/runner/work/serenity-js-realworld-app-demo/serenity-js-realworld-app-demo/spec/todo-list-app/TodoApp/tasks.ts"}},"sceneId":"unknown","timestamp":"2024-06-17T21:13:26.866Z"}},{"type":"InteractionFinished","value":{"activityId":"c1mtitouh4atvzkibc2v08se","details":{"name":"Alice navigates to '/'","location":{"column":18,"line":9,"path":"/home/runner/work/serenity-js-realworld-app-demo/serenity-js-realworld-app-demo/spec/todo-list-app/TodoApp/tasks.ts"}},"outcome":{"code":64},"sceneId":"unknown","timestamp":"2024-06-17T21:13:27.059Z"}},{"type":"InteractionStarts","value":{"activityId":"qgzuiyj33z4olprsxr9f1814","details":{"name":"Alice ensures that website title does equal 'Serenity/JS TodoApp'","location":{"column":37,"line":83,"path":"/home/runner/work/serenity-js-realworld-app-demo/serenity-js-realworld-app-demo/spec/recording_items.spec.ts"}},"sceneId":"unknown","timestamp":"2024-06-17T21:13:27.070Z"}},{"type":"InteractionFinished","value":{"activityId":"qgzuiyj33z4olprsxr9f1814","details":{"name":"Alice ensures that website title does equal 'Serenity/JS TodoApp'","location":{"column":37,"line":83,"path":"/home/runner/work/serenity-js-realworld-app-demo/serenity-js-realworld-app-demo/spec/recording_items.spec.ts"}},"outcome":{"code":64},"sceneId":"unknown","timestamp":"2024-06-17T21:13:27.075Z"}},{"type":"TaskFinished","value":{"activityId":"tjky3dgtomj6jxzzd7j51dm8","details":{"name":"Alice starts with an empty todo list","location":{"column":37,"line":83,"path":"/home/runner/work/serenity-js-realworld-app-demo/serenity-js-realworld-app-demo/spec/recording_items.spec.ts"}},"outcome":{"code":64},"sceneId":"unknown","timestamp":"2024-06-17T21:13:27.085Z"}},{"type":"InteractionStarts","value":{"activityId":"m50cjqvww5m5iu0fk49i7pga","details":{"name":"Alice ensures that main section does not become present","location":{"column":24,"line":85,"path":"/home/runner/work/serenity-js-realworld-app-demo/serenity-js-realworld-app-demo/spec/recording_items.spec.ts"}},"sceneId":"unknown","timestamp":"2024-06-17T21:13:27.096Z"}},{"type":"InteractionFinished","value":{"activityId":"m50cjqvww5m5iu0fk49i7pga","details":{"name":"Alice ensures that main section does not become present","location":{"column":24,"line":85,"path":"/home/runner/work/serenity-js-realworld-app-demo/serenity-js-realworld-app-demo/spec/recording_items.spec.ts"}},"outcome":{"code":64},"sceneId":"unknown","timestamp":"2024-06-17T21:13:27.352Z"}},{"type":"InteractionStarts","value":{"activityId":"japzix4bxuz9kb1mv29rac3c","details":{"name":"Alice ensures that footer section does not become present","location":{"column":24,"line":86,"path":"/home/runner/work/serenity-js-realworld-app-demo/serenity-js-realworld-app-demo/spec/recording_items.spec.ts"}},"sceneId":"unknown","timestamp":"2024-06-17T21:13:27.363Z"}},{"type":"InteractionFinished","value":{"activityId":"japzix4bxuz9kb1mv29rac3c","details":{"name":"Alice ensures that footer section does not become present","location":{"column":24,"line":86,"path":"/home/runner/work/serenity-js-realworld-app-demo/serenity-js-realworld-app-demo/spec/recording_items.spec.ts"}},"outcome":{"code":64},"sceneId":"unknown","timestamp":"2024-06-17T21:13:27.615Z"}},{"type":"TaskStarts","value":{"activityId":"bj5s3jb0y4nc9k063i6ffqlg","details":{"name":"Alice records an item called 'buy some cheese'","location":{"column":27,"line":88,"path":"/home/runner/work/serenity-js-realworld-app-demo/serenity-js-realworld-app-demo/spec/recording_items.spec.ts"}},"sceneId":"unknown","timestamp":"2024-06-17T21:13:27.626Z"}},{"type":"InteractionStarts","value":{"activityId":"jad3cpup4s92k027w23tyzjy","details":{"name":"Alice enters 'buy some cheese' into \"What needs to be done?\" input box","location":{"column":30,"line":12,"path":"/home/runner/work/serenity-js-realworld-app-demo/serenity-js-realworld-app-demo/spec/todo-list-app/TodoItem/tasks.ts"}},"sceneId":"unknown","timestamp":"2024-06-17T21:13:27.627Z"}},{"type":"InteractionFinished","value":{"activityId":"jad3cpup4s92k027w23tyzjy","details":{"name":"Alice enters 'buy some cheese' into \"What needs to be done?\" input box","location":{"column":30,"line":12,"path":"/home/runner/work/serenity-js-realworld-app-demo/serenity-js-realworld-app-demo/spec/todo-list-app/TodoItem/tasks.ts"}},"outcome":{"code":64},"sceneId":"unknown","timestamp":"2024-06-17T21:13:27.640Z"}},{"type":"InteractionStarts","value":{"activityId":"xf17c0mrm9nsiy1ei4j1jjye","details":{"name":"Alice presses key Enter in \"What needs to be done?\" input box","location":{"column":32,"line":13,"path":"/home/runner/work/serenity-js-realworld-app-demo/serenity-js-realworld-app-demo/spec/todo-list-app/TodoItem/tasks.ts"}},"sceneId":"unknown","timestamp":"2024-06-17T21:13:27.650Z"}},{"type":"InteractionFinished","value":{"activityId":"xf17c0mrm9nsiy1ei4j1jjye","details":{"name":"Alice presses key Enter in \"What needs to be done?\" input box","location":{"column":32,"line":13,"path":"/home/runner/work/serenity-js-realworld-app-demo/serenity-js-realworld-app-demo/spec/todo-list-app/TodoItem/tasks.ts"}},"outcome":{"code":64},"sceneId":"unknown","timestamp":"2024-06-17T21:13:27.674Z"}},{"type":"InteractionStarts","value":{"activityId":"zac1jbyoubtpzvcq56vtuebx","details":{"name":"Alice waits until displayed items does contain 'buy some cheese'","location":{"column":14,"line":14,"path":"/home/runner/work/serenity-js-realworld-app-demo/serenity-js-realworld-app-demo/spec/todo-list-app/TodoItem/tasks.ts"}},"sceneId":"unknown","timestamp":"2024-06-17T21:13:27.685Z"}},{"type":"InteractionFinished","value":{"activityId":"zac1jbyoubtpzvcq56vtuebx","details":{"name":"Alice waits until displayed items does contain 'buy some cheese'","location":{"column":14,"line":14,"path":"/home/runner/work/serenity-js-realworld-app-demo/serenity-js-realworld-app-demo/spec/todo-list-app/TodoItem/tasks.ts"}},"outcome":{"code":64},"sceneId":"unknown","timestamp":"2024-06-17T21:13:27.703Z"}},{"type":"TaskFinished","value":{"activityId":"bj5s3jb0y4nc9k063i6ffqlg","details":{"name":"Alice records an item called 'buy some cheese'","location":{"column":27,"line":88,"path":"/home/runner/work/serenity-js-realworld-app-demo/serenity-js-realworld-app-demo/spec/recording_items.spec.ts"}},"outcome":{"code":64},"sceneId":"unknown","timestamp":"2024-06-17T21:13:27.713Z"}},{"type":"InteractionStarts","value":{"activityId":"u95dm3ch4sgw14taadmmtz6j","details":{"name":"Alice ensures that main section does become visible","location":{"column":24,"line":90,"path":"/home/runner/work/serenity-js-realworld-app-demo/serenity-js-realworld-app-demo/spec/recording_items.spec.ts"}},"sceneId":"unknown","timestamp":"2024-06-17T21:13:27.724Z"}},{"type":"InteractionFinished","value":{"activityId":"u95dm3ch4sgw14taadmmtz6j","details":{"name":"Alice ensures that main section does become visible","location":{"column":24,"line":90,"path":"/home/runner/work/serenity-js-realworld-app-demo/serenity-js-realworld-app-demo/spec/recording_items.spec.ts"}},"outcome":{"code":64},"sceneId":"unknown","timestamp":"2024-06-17T21:13:27.743Z"}},{"type":"InteractionStarts","value":{"activityId":"u93zedbjinksh6xnederepxm","details":{"name":"Alice ensures that footer section does become visible","location":{"column":24,"line":91,"path":"/home/runner/work/serenity-js-realworld-app-demo/serenity-js-realworld-app-demo/spec/recording_items.spec.ts"}},"sceneId":"unknown","timestamp":"2024-06-17T21:13:27.753Z"}},{"type":"InteractionFinished","value":{"activityId":"u93zedbjinksh6xnederepxm","details":{"name":"Alice ensures that footer section does become visible","location":{"column":24,"line":91,"path":"/home/runner/work/serenity-js-realworld-app-demo/serenity-js-realworld-app-demo/spec/recording_items.spec.ts"}},"outcome":{"code":64},"sceneId":"unknown","timestamp":"2024-06-17T21:13:27.769Z"}},{"type":"SceneFinishes","value":{"sceneId":"unknown","timestamp":"2024-06-17T21:13:27.780Z"}},{"type":"AsyncOperationAttempted","value":{"correlationId":"bas826wn07ox5rgfrbwfrhkr","description":"Dismissing Alice...","name":"Stage","timestamp":"2024-06-17T21:13:27.790Z"}},{"type":"AsyncOperationCompleted","value":{"correlationId":"bas826wn07ox5rgfrbwfrhkr","timestamp":"2024-06-17T21:13:27.790Z"}}]