[{"type":"SceneTagged","value":{"sceneId":"unknown","tag":{"name":"Linux 6.5.0-1018-azure","type":"platform","platformName":"Linux","platformVersion":"6.5.0-1018-azure"},"timestamp":"2024-04-18T20:44:00.387Z"}},{"type":"SceneTagged","value":{"sceneId":"unknown","tag":{"name":"firefox 121.0","type":"browser","browserName":"firefox","browserVersion":"121.0"},"timestamp":"2024-04-18T20:44:00.552Z"}},{"type":"TaskStarts","value":{"activityId":"kba6ke9n6dv19u8wks4gixey","details":{"name":"Alice starts with a list containing 3 items","location":{"column":41,"line":74,"path":"/home/runner/work/serenity-js-realworld-app-demo/serenity-js-realworld-app-demo/spec/recording_items.spec.ts"}},"sceneId":"unknown","timestamp":"2024-04-18T20:44:00.575Z"}},{"type":"TaskStarts","value":{"activityId":"kr6i6niwci22lgzbn0qh1jb1","details":{"name":"Alice starts with an empty todo list","location":{"column":9,"line":18,"path":"/home/runner/work/serenity-js-realworld-app-demo/serenity-js-realworld-app-demo/spec/todo-list-app/TodoApp/tasks.ts"}},"sceneId":"unknown","timestamp":"2024-04-18T20:44:00.575Z"}},{"type":"InteractionStarts","value":{"activityId":"p8b2giwg2ejxmpsm7cflrdj3","details":{"name":"Alice navigates to '/'","location":{"column":18,"line":9,"path":"/home/runner/work/serenity-js-realworld-app-demo/serenity-js-realworld-app-demo/spec/todo-list-app/TodoApp/tasks.ts"}},"sceneId":"unknown","timestamp":"2024-04-18T20:44:00.576Z"}},{"type":"InteractionFinished","value":{"activityId":"p8b2giwg2ejxmpsm7cflrdj3","details":{"name":"Alice navigates to '/'","location":{"column":18,"line":9,"path":"/home/runner/work/serenity-js-realworld-app-demo/serenity-js-realworld-app-demo/spec/todo-list-app/TodoApp/tasks.ts"}},"outcome":{"code":64},"sceneId":"unknown","timestamp":"2024-04-18T20:44:00.731Z"}},{"type":"InteractionStarts","value":{"activityId":"mou1ioax7ss8fob7eemccjt7","details":{"name":"Alice ensures that website title does equal 'Serenity/JS TodoApp'","location":{"column":41,"line":74,"path":"/home/runner/work/serenity-js-realworld-app-demo/serenity-js-realworld-app-demo/spec/recording_items.spec.ts"}},"sceneId":"unknown","timestamp":"2024-04-18T20:44:00.742Z"}},{"type":"InteractionFinished","value":{"activityId":"mou1ioax7ss8fob7eemccjt7","details":{"name":"Alice ensures that website title does equal 'Serenity/JS TodoApp'","location":{"column":41,"line":74,"path":"/home/runner/work/serenity-js-realworld-app-demo/serenity-js-realworld-app-demo/spec/recording_items.spec.ts"}},"outcome":{"code":64},"sceneId":"unknown","timestamp":"2024-04-18T20:44:00.747Z"}},{"type":"TaskFinished","value":{"activityId":"kr6i6niwci22lgzbn0qh1jb1","details":{"name":"Alice starts with an empty todo list","location":{"column":9,"line":18,"path":"/home/runner/work/serenity-js-realworld-app-demo/serenity-js-realworld-app-demo/spec/todo-list-app/TodoApp/tasks.ts"}},"outcome":{"code":64},"sceneId":"unknown","timestamp":"2024-04-18T20:44:00.757Z"}},{"type":"TaskStarts","value":{"activityId":"a7dbve5blzd1bh3755u0l15p","details":{"name":"Alice records an item called 'buy some cheese'","location":{"column":18,"line":19,"path":"/home/runner/work/serenity-js-realworld-app-demo/serenity-js-realworld-app-demo/spec/todo-list-app/TodoApp/tasks.ts"}},"sceneId":"unknown","timestamp":"2024-04-18T20:44:00.768Z"}},{"type":"InteractionStarts","value":{"activityId":"notxt0jtwlxtc4s15yhm0p16","details":{"name":"Alice enters 'buy some cheese' into \"What needs to be done?\" input box","location":{"column":30,"line":12,"path":"/home/runner/work/serenity-js-realworld-app-demo/serenity-js-realworld-app-demo/spec/todo-list-app/TodoItem/tasks.ts"}},"sceneId":"unknown","timestamp":"2024-04-18T20:44:00.769Z"}},{"type":"InteractionFinished","value":{"activityId":"notxt0jtwlxtc4s15yhm0p16","details":{"name":"Alice enters 'buy some cheese' into \"What needs to be done?\" input box","location":{"column":30,"line":12,"path":"/home/runner/work/serenity-js-realworld-app-demo/serenity-js-realworld-app-demo/spec/todo-list-app/TodoItem/tasks.ts"}},"outcome":{"code":64},"sceneId":"unknown","timestamp":"2024-04-18T20:44:00.804Z"}},{"type":"InteractionStarts","value":{"activityId":"w356ytmsca64viq8co7q7big","details":{"name":"Alice presses key Enter in \"What needs to be done?\" input box","location":{"column":32,"line":13,"path":"/home/runner/work/serenity-js-realworld-app-demo/serenity-js-realworld-app-demo/spec/todo-list-app/TodoItem/tasks.ts"}},"sceneId":"unknown","timestamp":"2024-04-18T20:44:00.815Z"}},{"type":"InteractionFinished","value":{"activityId":"w356ytmsca64viq8co7q7big","details":{"name":"Alice presses key Enter in \"What needs to be done?\" input box","location":{"column":32,"line":13,"path":"/home/runner/work/serenity-js-realworld-app-demo/serenity-js-realworld-app-demo/spec/todo-list-app/TodoItem/tasks.ts"}},"outcome":{"code":64},"sceneId":"unknown","timestamp":"2024-04-18T20:44:00.854Z"}},{"type":"InteractionStarts","value":{"activityId":"e5hulooekmu09yw5d6kzznpa","details":{"name":"Alice waits until displayed items does contain 'buy some cheese'","location":{"column":14,"line":14,"path":"/home/runner/work/serenity-js-realworld-app-demo/serenity-js-realworld-app-demo/spec/todo-list-app/TodoItem/tasks.ts"}},"sceneId":"unknown","timestamp":"2024-04-18T20:44:00.866Z"}},{"type":"InteractionFinished","value":{"activityId":"e5hulooekmu09yw5d6kzznpa","details":{"name":"Alice waits until displayed items does contain 'buy some cheese'","location":{"column":14,"line":14,"path":"/home/runner/work/serenity-js-realworld-app-demo/serenity-js-realworld-app-demo/spec/todo-list-app/TodoItem/tasks.ts"}},"outcome":{"code":64},"sceneId":"unknown","timestamp":"2024-04-18T20:44:00.887Z"}},{"type":"TaskFinished","value":{"activityId":"a7dbve5blzd1bh3755u0l15p","details":{"name":"Alice records an item called 'buy some cheese'","location":{"column":18,"line":19,"path":"/home/runner/work/serenity-js-realworld-app-demo/serenity-js-realworld-app-demo/spec/todo-list-app/TodoApp/tasks.ts"}},"outcome":{"code":64},"sceneId":"unknown","timestamp":"2024-04-18T20:44:00.897Z"}},{"type":"TaskStarts","value":{"activityId":"w8o49x4e3i59haoclr4uppku","details":{"name":"Alice records an item called 'feed the cat'","location":{"column":18,"line":19,"path":"/home/runner/work/serenity-js-realworld-app-demo/serenity-js-realworld-app-demo/spec/todo-list-app/TodoApp/tasks.ts"}},"sceneId":"unknown","timestamp":"2024-04-18T20:44:00.908Z"}},{"type":"InteractionStarts","value":{"activityId":"m4aj5b0w1er4w7m6owxwc74x","details":{"name":"Alice enters 'feed the cat' into \"What needs to be done?\" input box","location":{"column":30,"line":12,"path":"/home/runner/work/serenity-js-realworld-app-demo/serenity-js-realworld-app-demo/spec/todo-list-app/TodoItem/tasks.ts"}},"sceneId":"unknown","timestamp":"2024-04-18T20:44:00.909Z"}},{"type":"InteractionFinished","value":{"activityId":"m4aj5b0w1er4w7m6owxwc74x","details":{"name":"Alice enters 'feed the cat' into \"What needs to be done?\" input box","location":{"column":30,"line":12,"path":"/home/runner/work/serenity-js-realworld-app-demo/serenity-js-realworld-app-demo/spec/todo-list-app/TodoItem/tasks.ts"}},"outcome":{"code":64},"sceneId":"unknown","timestamp":"2024-04-18T20:44:00.922Z"}},{"type":"InteractionStarts","value":{"activityId":"uzxk17p0guveurd1vlnwremy","details":{"name":"Alice presses key Enter in \"What needs to be done?\" input box","location":{"column":32,"line":13,"path":"/home/runner/work/serenity-js-realworld-app-demo/serenity-js-realworld-app-demo/spec/todo-list-app/TodoItem/tasks.ts"}},"sceneId":"unknown","timestamp":"2024-04-18T20:44:00.933Z"}},{"type":"InteractionFinished","value":{"activityId":"uzxk17p0guveurd1vlnwremy","details":{"name":"Alice presses key Enter in \"What needs to be done?\" input box","location":{"column":32,"line":13,"path":"/home/runner/work/serenity-js-realworld-app-demo/serenity-js-realworld-app-demo/spec/todo-list-app/TodoItem/tasks.ts"}},"outcome":{"code":64},"sceneId":"unknown","timestamp":"2024-04-18T20:44:00.952Z"}},{"type":"InteractionStarts","value":{"activityId":"ctv5m53bwyzuvfgywborph1z","details":{"name":"Alice waits until displayed items does contain 'feed the cat'","location":{"column":14,"line":14,"path":"/home/runner/work/serenity-js-realworld-app-demo/serenity-js-realworld-app-demo/spec/todo-list-app/TodoItem/tasks.ts"}},"sceneId":"unknown","timestamp":"2024-04-18T20:44:00.963Z"}},{"type":"InteractionFinished","value":{"activityId":"ctv5m53bwyzuvfgywborph1z","details":{"name":"Alice waits until displayed items does contain 'feed the cat'","location":{"column":14,"line":14,"path":"/home/runner/work/serenity-js-realworld-app-demo/serenity-js-realworld-app-demo/spec/todo-list-app/TodoItem/tasks.ts"}},"outcome":{"code":64},"sceneId":"unknown","timestamp":"2024-04-18T20:44:00.986Z"}},{"type":"TaskFinished","value":{"activityId":"w8o49x4e3i59haoclr4uppku","details":{"name":"Alice records an item called 'feed the cat'","location":{"column":18,"line":19,"path":"/home/runner/work/serenity-js-realworld-app-demo/serenity-js-realworld-app-demo/spec/todo-list-app/TodoApp/tasks.ts"}},"outcome":{"code":64},"sceneId":"unknown","timestamp":"2024-04-18T20:44:00.996Z"}},{"type":"TaskStarts","value":{"activityId":"zech1w463u0ksxyrred63op4","details":{"name":"Alice records an item called 'book a doctors appointment'","location":{"column":18,"line":19,"path":"/home/runner/work/serenity-js-realworld-app-demo/serenity-js-realworld-app-demo/spec/todo-list-app/TodoApp/tasks.ts"}},"sceneId":"unknown","timestamp":"2024-04-18T20:44:01.007Z"}},{"type":"InteractionStarts","value":{"activityId":"rg543hhy6wl4yw3q19ppumly","details":{"name":"Alice enters 'book a doctors appointment' into \"What needs to be done?\" input box","location":{"column":30,"line":12,"path":"/home/runner/work/serenity-js-realworld-app-demo/serenity-js-realworld-app-demo/spec/todo-list-app/TodoItem/tasks.ts"}},"sceneId":"unknown","timestamp":"2024-04-18T20:44:01.008Z"}},{"type":"InteractionFinished","value":{"activityId":"rg543hhy6wl4yw3q19ppumly","details":{"name":"Alice enters 'book a doctors appointment' into \"What needs to be done?\" input box","location":{"column":30,"line":12,"path":"/home/runner/work/serenity-js-realworld-app-demo/serenity-js-realworld-app-demo/spec/todo-list-app/TodoItem/tasks.ts"}},"outcome":{"code":64},"sceneId":"unknown","timestamp":"2024-04-18T20:44:01.020Z"}},{"type":"InteractionStarts","value":{"activityId":"mtwhhrg3j24dvlle1rdlctgz","details":{"name":"Alice presses key Enter in \"What needs to be done?\" input box","location":{"column":32,"line":13,"path":"/home/runner/work/serenity-js-realworld-app-demo/serenity-js-realworld-app-demo/spec/todo-list-app/TodoItem/tasks.ts"}},"sceneId":"unknown","timestamp":"2024-04-18T20:44:01.031Z"}},{"type":"InteractionFinished","value":{"activityId":"mtwhhrg3j24dvlle1rdlctgz","details":{"name":"Alice presses key Enter in \"What needs to be done?\" input box","location":{"column":32,"line":13,"path":"/home/runner/work/serenity-js-realworld-app-demo/serenity-js-realworld-app-demo/spec/todo-list-app/TodoItem/tasks.ts"}},"outcome":{"code":64},"sceneId":"unknown","timestamp":"2024-04-18T20:44:01.046Z"}},{"type":"InteractionStarts","value":{"activityId":"z6uai7ev02u25skiyhbozopf","details":{"name":"Alice waits until displayed items does contain 'book a doctors appointment'","location":{"column":14,"line":14,"path":"/home/runner/work/serenity-js-realworld-app-demo/serenity-js-realworld-app-demo/spec/todo-list-app/TodoItem/tasks.ts"}},"sceneId":"unknown","timestamp":"2024-04-18T20:44:01.058Z"}},{"type":"InteractionFinished","value":{"activityId":"z6uai7ev02u25skiyhbozopf","details":{"name":"Alice waits until displayed items does contain 'book a doctors appointment'","location":{"column":14,"line":14,"path":"/home/runner/work/serenity-js-realworld-app-demo/serenity-js-realworld-app-demo/spec/todo-list-app/TodoItem/tasks.ts"}},"outcome":{"code":64},"sceneId":"unknown","timestamp":"2024-04-18T20:44:01.087Z"}},{"type":"TaskFinished","value":{"activityId":"zech1w463u0ksxyrred63op4","details":{"name":"Alice records an item called 'book a doctors appointment'","location":{"column":18,"line":19,"path":"/home/runner/work/serenity-js-realworld-app-demo/serenity-js-realworld-app-demo/spec/todo-list-app/TodoApp/tasks.ts"}},"outcome":{"code":64},"sceneId":"unknown","timestamp":"2024-04-18T20:44:01.097Z"}},{"type":"TaskFinished","value":{"activityId":"kba6ke9n6dv19u8wks4gixey","details":{"name":"Alice starts with a list containing 3 items","location":{"column":41,"line":74,"path":"/home/runner/work/serenity-js-realworld-app-demo/serenity-js-realworld-app-demo/spec/recording_items.spec.ts"}},"outcome":{"code":64},"sceneId":"unknown","timestamp":"2024-04-18T20:44:01.107Z"}},{"type":"InteractionStarts","value":{"activityId":"jezkel243xntmnyrriyh60yz","details":{"name":"Alice ensures that number of items left does equal 3","location":{"column":24,"line":76,"path":"/home/runner/work/serenity-js-realworld-app-demo/serenity-js-realworld-app-demo/spec/recording_items.spec.ts"}},"sceneId":"unknown","timestamp":"2024-04-18T20:44:01.118Z"}},{"type":"InteractionFinished","value":{"activityId":"jezkel243xntmnyrriyh60yz","details":{"name":"Alice ensures that number of items left does equal 3","location":{"column":24,"line":76,"path":"/home/runner/work/serenity-js-realworld-app-demo/serenity-js-realworld-app-demo/spec/recording_items.spec.ts"}},"outcome":{"code":64},"sceneId":"unknown","timestamp":"2024-04-18T20:44:01.124Z"}},{"type":"InteractionStarts","value":{"activityId":"twtztt930k7rvj2uxlugczed","details":{"name":"Alice ensures that <<persisted items>>.length does equal 3","location":{"column":24,"line":77,"path":"/home/runner/work/serenity-js-realworld-app-demo/serenity-js-realworld-app-demo/spec/recording_items.spec.ts"}},"sceneId":"unknown","timestamp":"2024-04-18T20:44:01.135Z"}},{"type":"InteractionFinished","value":{"activityId":"twtztt930k7rvj2uxlugczed","details":{"name":"Alice ensures that <<persisted items>>.length does equal 3","location":{"column":24,"line":77,"path":"/home/runner/work/serenity-js-realworld-app-demo/serenity-js-realworld-app-demo/spec/recording_items.spec.ts"}},"outcome":{"code":64},"sceneId":"unknown","timestamp":"2024-04-18T20:44:01.139Z"}},{"type":"SceneFinishes","value":{"sceneId":"unknown","timestamp":"2024-04-18T20:44:01.150Z"}},{"type":"AsyncOperationAttempted","value":{"correlationId":"eguljpy6rg5p3uduhzj83ul7","description":"Dismissing Alice...","name":"Stage","timestamp":"2024-04-18T20:44:01.160Z"}},{"type":"AsyncOperationCompleted","value":{"correlationId":"eguljpy6rg5p3uduhzj83ul7","timestamp":"2024-04-18T20:44:01.160Z"}}]